{
  "fetchedAt": "2026-05-11T17:32:56.346Z",
  "elapsedMs": 1845,
  "sourceTotal": 7,
  "sourceSuccess": 7,
  "sourceFail": 0,
  "totalHeadlines": 359,
  "uniqueKeywords": 296,
  "multiSourceCount": 100,
  "sources": [
    {
      "id": "sbs",
      "name": "SBS",
      "url": "https://news.sbs.co.kr/news/SectionRssFeed.do?sectionId=01",
      "status": "ok",
      "itemCount": 29,
      "elapsedMs": 144
    },
    {
      "id": "yna",
      "name": "연합뉴스",
      "url": "https://www.yna.co.kr/rss/news.xml",
      "status": "ok",
      "itemCount": 120,
      "elapsedMs": 1330
    },
    {
      "id": "donga",
      "name": "동아일보",
      "url": "https://rss.donga.com/total.xml",
      "status": "ok",
      "itemCount": 50,
      "elapsedMs": 1755
    },
    {
      "id": "khan",
      "name": "경향신문",
      "url": "https://www.khan.co.kr/rss/rssdata/total_news.xml",
      "status": "ok",
      "itemCount": 50,
      "elapsedMs": 1378
    },
    {
      "id": "mk",
      "name": "매일경제",
      "url": "https://www.mk.co.kr/rss/30000001/",
      "status": "ok",
      "itemCount": 50,
      "elapsedMs": 1560
    },
    {
      "id": "kmib",
      "name": "국민일보",
      "url": "https://www.kmib.co.kr/rss/data/kmibRssAll.xml",
      "status": "ok",
      "itemCount": 30,
      "elapsedMs": 1690
    },
    {
      "id": "hani",
      "name": "한겨레",
      "url": "https://www.hani.co.kr/rss",
      "status": "ok",
      "itemCount": 30,
      "elapsedMs": 1774
    }
  ],
  "multiSourceKeywords": [
    {
      "term": "이란",
      "total": 17,
      "sourceCount": 6,
      "sources": [
        "sbs",
        "yna",
        "donga",
        "khan",
        "mk",
        "hani"
      ],
      "examples": [
        {
          "source": "sbs",
          "title": "정치권도 '나무호 공방'…이란 소행 가능성에도 '신중론'"
        },
        {
          "source": "sbs",
          "title": "청와대 \"나무호 공격 규탄\"…이란 관련성엔 \"미지 영역\""
        },
        {
          "source": "yna",
          "title": "트럼프 \"해방 프로젝트 재개 검토\"…규모 확대 시사로 이란 압박"
        }
      ]
    },
    {
      "term": "트럼프",
      "total": 19,
      "sourceCount": 5,
      "sources": [
        "yna",
        "donga",
        "khan",
        "mk",
        "hani"
      ],
      "examples": [
        {
          "source": "yna",
          "title": "트럼프 \"이란과의 휴전 간신히 유지…해방 프로젝트 재개 검토\"(종합)"
        },
        {
          "source": "yna",
          "title": "트럼프 방중 수행단에 테슬라·애플 CEO 합류…엔비디아는 빠져"
        },
        {
          "source": "yna",
          "title": "러 \"트럼프 방러 초청 여전히 유효, 푸틴이 환영할 것\"(종합)"
        }
      ]
    },
    {
      "term": "나무호",
      "total": 14,
      "sourceCount": 5,
      "sources": [
        "sbs",
        "donga",
        "khan",
        "mk",
        "hani"
      ],
      "examples": [
        {
          "source": "sbs",
          "title": "정치권도 '나무호 공방'…이란 소행 가능성에도 '신중론'"
        },
        {
          "source": "sbs",
          "title": "청와대 \"나무호 공격 규탄\"…이란 관련성엔 \"미지 영역\""
        },
        {
          "source": "sbs",
          "title": "여야 '나무호 피격' 상임위 소집 공방…\"자해행위\"·\"사실은폐\""
        }
      ]
    },
    {
      "term": "삼성전자",
      "total": 7,
      "sourceCount": 5,
      "sources": [
        "yna",
        "donga",
        "khan",
        "mk",
        "hani"
      ],
      "examples": [
        {
          "source": "yna",
          "title": "삼성전자 노사 사후조정 첫날 결론없이 종료…내일 최종 판가름(종합)"
        },
        {
          "source": "yna",
          "title": "삼성전자 노사, 사후조정 첫날 회의 종료…12일 재개"
        },
        {
          "source": "donga",
          "title": "삼성전자 노사, 사후조정 첫날 12시간만에 종료…내일 재개"
        }
      ]
    },
    {
      "term": "노사",
      "total": 7,
      "sourceCount": 5,
      "sources": [
        "yna",
        "donga",
        "khan",
        "mk",
        "hani"
      ],
      "examples": [
        {
          "source": "yna",
          "title": "삼성전자 노사 사후조정 첫날 결론없이 종료…내일 최종 판가름(종합)"
        },
        {
          "source": "yna",
          "title": "삼성전자 노사, 사후조정 첫날 회의 종료…12일 재개"
        },
        {
          "source": "donga",
          "title": "삼성전자 노사, 사후조정 첫날 12시간만에 종료…내일 재개"
        }
      ]
    },
    {
      "term": "재개",
      "total": 9,
      "sourceCount": 4,
      "sources": [
        "yna",
        "donga",
        "mk",
        "hani"
      ],
      "examples": [
        {
          "source": "yna",
          "title": "트럼프 \"이란과의 휴전 간신히 유지…해방 프로젝트 재개 검토\"(종합)"
        },
        {
          "source": "yna",
          "title": "트럼프 \"해방 프로젝트 재개 검토\"…규모 확대 시사로 이란 압박"
        },
        {
          "source": "yna",
          "title": "[속보] 트럼프 \"해방 프로젝트, 더 큰 규모로 재개 검토\" <폭스뉴스>"
        }
      ]
    },
    {
      "term": "합의",
      "total": 7,
      "sourceCount": 4,
      "sources": [
        "yna",
        "donga",
        "khan",
        "mk"
      ],
      "examples": [
        {
          "source": "yna",
          "title": "EU, '요르단강 서안 폭력' 이스라엘 정착민 제재 합의(종합)"
        },
        {
          "source": "yna",
          "title": "EU, '서안지구 폭력' 이스라엘 정착민 제재 합의"
        },
        {
          "source": "yna",
          "title": "러·우크라, 또 휴전 공방…합의 위반 '네탓'(종합)"
        }
      ]
    },
    {
      "term": "공약",
      "total": 5,
      "sourceCount": 4,
      "sources": [
        "sbs",
        "yna",
        "khan",
        "hani"
      ],
      "examples": [
        {
          "source": "sbs",
          "title": "정원오 '15분 AI' 공약…오세훈 양자토론 요구엔 \"상황 따라 말 바꿔\""
        },
        {
          "source": "yna",
          "title": "우상호 \"공약 파기 사과부터\" vs 김진태 \"현안 너무 모른다\""
        },
        {
          "source": "yna",
          "title": "정원오 '15분 AI' 공약…吳 양자토론 압박엔 \"상황따라 말바꿔\"(종합)"
        }
      ]
    },
    {
      "term": "영상",
      "total": 5,
      "sourceCount": 4,
      "sources": [
        "sbs",
        "yna",
        "khan",
        "mk"
      ],
      "examples": [
        {
          "source": "sbs",
          "title": "촬영 기자 발 헛디뎌 떨어지는데…한동훈 '무신경' 논란 영상 보니 [자막뉴스]"
        },
        {
          "source": "yna",
          "title": "[영상] 한국 상선 덮친 '미상의 비행체'…정부의 대응 카드는"
        },
        {
          "source": "khan",
          "title": "‘약물 성범죄’ 영상 증거에도…검찰 “불기소”"
        }
      ]
    },
    {
      "term": "호르무즈",
      "total": 5,
      "sourceCount": 4,
      "sources": [
        "yna",
        "donga",
        "khan",
        "hani"
      ],
      "examples": [
        {
          "source": "yna",
          "title": "나토 회원국 리투아니아, 호르무즈 파병 추진"
        },
        {
          "source": "yna",
          "title": "영·프, 호르무즈 항행 지원 국방장관 회의 연다…\"40여개국 참여\""
        },
        {
          "source": "donga",
          "title": "트럼프 “호르무즈 해방작전 재개 검토…더 강력조치 취할수도”"
        }
      ]
    },
    {
      "term": "사후조정",
      "total": 5,
      "sourceCount": 4,
      "sources": [
        "yna",
        "donga",
        "khan",
        "mk"
      ],
      "examples": [
        {
          "source": "yna",
          "title": "삼성전자 노사 사후조정 첫날 결론없이 종료…내일 최종 판가름(종합)"
        },
        {
          "source": "yna",
          "title": "삼성전자 노사, 사후조정 첫날 회의 종료…12일 재개"
        },
        {
          "source": "donga",
          "title": "삼성전자 노사, 사후조정 첫날 12시간만에 종료…내일 재개"
        }
      ]
    },
    {
      "term": "첫날",
      "total": 5,
      "sourceCount": 4,
      "sources": [
        "yna",
        "donga",
        "khan",
        "mk"
      ],
      "examples": [
        {
          "source": "yna",
          "title": "삼성전자 노사 사후조정 첫날 결론없이 종료…내일 최종 판가름(종합)"
        },
        {
          "source": "yna",
          "title": "삼성전자 노사, 사후조정 첫날 회의 종료…12일 재개"
        },
        {
          "source": "donga",
          "title": "삼성전자 노사, 사후조정 첫날 12시간만에 종료…내일 재개"
        }
      ]
    },
    {
      "term": "회장",
      "total": 5,
      "sourceCount": 4,
      "sources": [
        "yna",
        "donga",
        "khan",
        "mk"
      ],
      "examples": [
        {
          "source": "yna",
          "title": "아르노 LVMH 회장, 신세계·롯데 매장 방문…롯데선 신동빈 동행(종합)"
        },
        {
          "source": "donga",
          "title": "루이뷔통 아르노 회장 부녀, 신세계百 본점 방문"
        },
        {
          "source": "khan",
          "title": "세계한상대회 총회 초대 의장에 하경서 회장 선임"
        }
      ]
    },
    {
      "term": "남극",
      "total": 4,
      "sourceCount": 4,
      "sources": [
        "yna",
        "khan",
        "mk",
        "hani"
      ],
      "examples": [
        {
          "source": "yna",
          "title": "남극 장보고기지 대원, 흉기로 동료위협…국내 이송돼 경찰 수사"
        },
        {
          "source": "khan",
          "title": "남극 장보고 과학기지서 흉기로 동료 위협한 대원 국내 이송···경찰 수사 착수"
        },
        {
          "source": "mk",
          "title": "흉기로 동료위협한 남극 장보고기지 대원…국내 이송돼 경찰 수사"
        }
      ]
    },
    {
      "term": "국내",
      "total": 4,
      "sourceCount": 4,
      "sources": [
        "yna",
        "donga",
        "khan",
        "mk"
      ],
      "examples": [
        {
          "source": "yna",
          "title": "남극 장보고기지 대원, 흉기로 동료위협…국내 이송돼 경찰 수사"
        },
        {
          "source": "donga",
          "title": "[애널리스트의 마켓뷰]삼전·닉스 2배 레버리지 ETF, 서학개미 국내 유턴의 계기 되나"
        },
        {
          "source": "khan",
          "title": "남극 장보고 과학기지서 흉기로 동료 위협한 대원 국내 이송···경찰 수사 착수"
        }
      ]
    },
    {
      "term": "국힘",
      "total": 4,
      "sourceCount": 4,
      "sources": [
        "yna",
        "khan",
        "mk",
        "hani"
      ],
      "examples": [
        {
          "source": "yna",
          "title": "김부겸 \"국힘 의원들과 힘 합치면…중앙 장벽 돌파 가능\""
        },
        {
          "source": "khan",
          "title": "민주당 “균형발전” 국힘 “주거 안정”…선관위, 6·3 지방선거 10대 공약 공개"
        },
        {
          "source": "mk",
          "title": "민주 \"균형발전\" 국힘 \"주거안정\""
        }
      ]
    },
    {
      "term": "남성",
      "total": 4,
      "sourceCount": 4,
      "sources": [
        "yna",
        "khan",
        "mk",
        "hani"
      ],
      "examples": [
        {
          "source": "yna",
          "title": "여성 행세하며 '명품 헐값 판매' 사기…20억원 가로챈 남성 입건"
        },
        {
          "source": "khan",
          "title": "‘트럼프 암살 시도’ 만찬장 총격 남성···재판에서 “무죄” 주장"
        },
        {
          "source": "mk",
          "title": "인천 아파트 단지서 초등생 강제추행 한 60대 남성"
        }
      ]
    },
    {
      "term": "공격",
      "total": 9,
      "sourceCount": 3,
      "sources": [
        "sbs",
        "mk",
        "hani"
      ],
      "examples": [
        {
          "source": "sbs",
          "title": "청와대 \"민간 선박 공격 규탄\"…대상은 특정 안 해"
        },
        {
          "source": "sbs",
          "title": "청와대 \"나무호 공격 규탄\"…이란 관련성엔 \"미지 영역\""
        },
        {
          "source": "sbs",
          "title": "청와대 \"나무호 등 공격 강력 규탄…안전보장 국제노력 동참\""
        }
      ]
    },
    {
      "term": "규탄",
      "total": 8,
      "sourceCount": 3,
      "sources": [
        "sbs",
        "mk",
        "hani"
      ],
      "examples": [
        {
          "source": "sbs",
          "title": "청와대 \"민간 선박 공격 규탄\"…대상은 특정 안 해"
        },
        {
          "source": "sbs",
          "title": "청와대 \"나무호 공격 규탄\"…이란 관련성엔 \"미지 영역\""
        },
        {
          "source": "sbs",
          "title": "청와대 \"나무호 등 공격 강력 규탄…안전보장 국제노력 동참\""
        }
      ]
    },
    {
      "term": "국방장관",
      "total": 7,
      "sourceCount": 3,
      "sources": [
        "yna",
        "donga",
        "khan"
      ],
      "examples": [
        {
          "source": "yna",
          "title": "韓美국방장관 워싱턴서 회담…전작권·핵잠·정보공유정상화 논의"
        },
        {
          "source": "yna",
          "title": "[속보] 한미 국방장관, 워싱턴서 회담 시작…전작권·핵잠협력 등 논의"
        },
        {
          "source": "yna",
          "title": "라트비아 국방장관 날린 우크라 드론…영공침범에 사임"
        }
      ]
    },
    {
      "term": "피격",
      "total": 6,
      "sourceCount": 3,
      "sources": [
        "sbs",
        "donga",
        "hani"
      ],
      "examples": [
        {
          "source": "sbs",
          "title": "여야 '나무호 피격' 상임위 소집 공방…\"자해행위\"·\"사실은폐\""
        },
        {
          "source": "sbs",
          "title": "[바로이뉴스] \"기뢰·어뢰 피격 가능성 낮아\"…\"'나무호' 공격 주체는\" 잠정 결론 나왔다"
        },
        {
          "source": "donga",
          "title": "[사설]나무호 피격 확인… 호르무즈에 갇힌 26척 안전이 최우선"
        }
      ]
    },
    {
      "term": "민주",
      "total": 6,
      "sourceCount": 3,
      "sources": [
        "sbs",
        "mk",
        "hani"
      ],
      "examples": [
        {
          "source": "sbs",
          "title": "민주, 서울·강원 공천자대회…\"거센 파란 바람 불어 탈환해야\""
        },
        {
          "source": "sbs",
          "title": "울산 집결한 국민의힘, 단일대오 과시…민주 김상욱에 \"배신자\" 직격"
        },
        {
          "source": "sbs",
          "title": "민주, 강원도에서 선대위 첫 회의…\"도민 눈 번쩍 뜨일 발전 약속\""
        }
      ]
    },
    {
      "term": "지방선거",
      "total": 6,
      "sourceCount": 3,
      "sources": [
        "yna",
        "khan",
        "hani"
      ],
      "examples": [
        {
          "source": "yna",
          "title": "지방선거 참패 후폭풍…노동당 내 반란 직면한 스타머"
        },
        {
          "source": "yna",
          "title": "'지방선거 참패' 스타머, 사임 압박 거부…영국 국채금리 상승"
        },
        {
          "source": "khan",
          "title": "지방선거 2석 → 1453석…‘영국의 트럼프’가 온다"
        }
      ]
    },
    {
      "term": "분기",
      "total": 6,
      "sourceCount": 3,
      "sources": [
        "yna",
        "donga",
        "khan"
      ],
      "examples": [
        {
          "source": "yna",
          "title": "한샘 1분기 영업이익 101억원…작년 동기 대비 56.4% 증가"
        },
        {
          "source": "yna",
          "title": "롯데케미칼 1분기 영업익 735억원…\"실적 개선세 지속\"(종합2보)"
        },
        {
          "source": "donga",
          "title": "백화점 외국인 매출 늘자… 롯데쇼핑 1분기 영업익 71% 껑충"
        }
      ]
    },
    {
      "term": "정원오",
      "total": 5,
      "sourceCount": 3,
      "sources": [
        "sbs",
        "yna",
        "khan"
      ],
      "examples": [
        {
          "source": "sbs",
          "title": "추미애 \"피해자 명예 회복 당연\"…정원오 \"입법부 일\""
        },
        {
          "source": "sbs",
          "title": "정원오 '15분 AI' 공약…오세훈 양자토론 요구엔 \"상황 따라 말 바꿔\""
        },
        {
          "source": "yna",
          "title": "정원오 \"서울을 청년들의 창업도시로…창업 클러스터 운영\""
        }
      ]
    },
    {
      "term": "해방",
      "total": 5,
      "sourceCount": 3,
      "sources": [
        "yna",
        "mk",
        "hani"
      ],
      "examples": [
        {
          "source": "yna",
          "title": "트럼프 \"이란과의 휴전 간신히 유지…해방 프로젝트 재개 검토\"(종합)"
        },
        {
          "source": "yna",
          "title": "트럼프 \"해방 프로젝트 재개 검토\"…규모 확대 시사로 이란 압박"
        },
        {
          "source": "yna",
          "title": "[속보] 트럼프 \"해방 프로젝트, 더 큰 규모로 재개 검토\" <폭스뉴스>"
        }
      ]
    },
    {
      "term": "프로젝트",
      "total": 5,
      "sourceCount": 3,
      "sources": [
        "yna",
        "mk",
        "hani"
      ],
      "examples": [
        {
          "source": "yna",
          "title": "트럼프 \"이란과의 휴전 간신히 유지…해방 프로젝트 재개 검토\"(종합)"
        },
        {
          "source": "yna",
          "title": "트럼프 \"해방 프로젝트 재개 검토\"…규모 확대 시사로 이란 압박"
        },
        {
          "source": "yna",
          "title": "[속보] 트럼프 \"해방 프로젝트, 더 큰 규모로 재개 검토\" <폭스뉴스>"
        }
      ]
    },
    {
      "term": "이스라엘",
      "total": 5,
      "sourceCount": 3,
      "sources": [
        "yna",
        "donga",
        "khan"
      ],
      "examples": [
        {
          "source": "yna",
          "title": "'성모상 입에 담배' 종교 모독 이스라엘 병사들 교도소행"
        },
        {
          "source": "yna",
          "title": "EU, '요르단강 서안 폭력' 이스라엘 정착민 제재 합의(종합)"
        },
        {
          "source": "yna",
          "title": "EU, '서안지구 폭력' 이스라엘 정착민 제재 합의"
        }
      ]
    },
    {
      "term": "박상용",
      "total": 5,
      "sourceCount": 3,
      "sources": [
        "yna",
        "mk",
        "hani"
      ],
      "examples": [
        {
          "source": "yna",
          "title": "'연어 술파티' 박상용 대검서 6시간 징계심의…朴 \"충실히 소명\"(종합2보)"
        },
        {
          "source": "yna",
          "title": "대검 감찰위, '연어 술파티' 박상용 징계심의…朴 \"충실히 소명\"(종합)"
        },
        {
          "source": "yna",
          "title": "법원 \"'박상용 분변 의혹'은 허위\"…국회의원 배상책임은 불인정"
        }
      ]
    },
    {
      "term": "의혹",
      "total": 5,
      "sourceCount": 3,
      "sources": [
        "yna",
        "khan",
        "hani"
      ],
      "examples": [
        {
          "source": "yna",
          "title": "검찰, 백해룡 '세관 직원 명예훼손' 의혹 수사 착수"
        },
        {
          "source": "yna",
          "title": "법원 \"'박상용 분변 의혹'은 허위\"…국회의원 배상책임은 불인정"
        },
        {
          "source": "khan",
          "title": "공수처, ‘룸살롱 접대 의혹’ 지귀연 조사"
        }
      ]
    },
    {
      "term": "공방",
      "total": 4,
      "sourceCount": 3,
      "sources": [
        "sbs",
        "yna",
        "mk"
      ],
      "examples": [
        {
          "source": "sbs",
          "title": "정치권도 '나무호 공방'…이란 소행 가능성에도 '신중론'"
        },
        {
          "source": "sbs",
          "title": "여야 '나무호 피격' 상임위 소집 공방…\"자해행위\"·\"사실은폐\""
        },
        {
          "source": "yna",
          "title": "러·우크라, 또 휴전 공방…합의 위반 '네탓'(종합)"
        }
      ]
    },
    {
      "term": "논란",
      "total": 4,
      "sourceCount": 3,
      "sources": [
        "sbs",
        "mk",
        "hani"
      ],
      "examples": [
        {
          "source": "sbs",
          "title": "[여담야담] 장동혁, 또 계엄 옹호 논란 발언…주광덕 \"2선 후퇴 안 하면 후보 등록 안 해\""
        },
        {
          "source": "sbs",
          "title": "촬영 기자 발 헛디뎌 떨어지는데…한동훈 '무신경' 논란 영상 보니 [자막뉴스]"
        },
        {
          "source": "mk",
          "title": "“저 여학생 몸매 ㅇㅇㅇ”…경북대 학생회 단톡방 성희롱 논란"
        }
      ]
    },
    {
      "term": "회의",
      "total": 4,
      "sourceCount": 3,
      "sources": [
        "sbs",
        "yna",
        "khan"
      ],
      "examples": [
        {
          "source": "sbs",
          "title": "민주, 강원도에서 선대위 첫 회의…\"도민 눈 번쩍 뜨일 발전 약속\""
        },
        {
          "source": "yna",
          "title": "삼성전자 노사, 사후조정 첫날 회의 종료…12일 재개"
        },
        {
          "source": "yna",
          "title": "영·프, 호르무즈 항행 지원 국방장관 회의 연다…\"40여개국 참여\""
        }
      ]
    },
    {
      "term": "압박",
      "total": 4,
      "sourceCount": 3,
      "sources": [
        "yna",
        "mk",
        "hani"
      ],
      "examples": [
        {
          "source": "yna",
          "title": "트럼프 \"해방 프로젝트 재개 검토\"…규모 확대 시사로 이란 압박"
        },
        {
          "source": "yna",
          "title": "'지방선거 참패' 스타머, 사임 압박 거부…영국 국채금리 상승"
        },
        {
          "source": "mk",
          "title": "트럼프 “해방 프로젝트 재개 검토”…규모 확대 시사로 이란 압박"
        }
      ]
    },
    {
      "term": "워싱턴서",
      "total": 4,
      "sourceCount": 3,
      "sources": [
        "yna",
        "donga",
        "khan"
      ],
      "examples": [
        {
          "source": "yna",
          "title": "韓美국방장관 워싱턴서 회담…전작권·핵잠·정보공유정상화 논의"
        },
        {
          "source": "yna",
          "title": "[속보] 한미 국방장관, 워싱턴서 회담 시작…전작권·핵잠협력 등 논의"
        },
        {
          "source": "donga",
          "title": "한미 국방장관, 워싱턴서 회담 돌입…전작권 전환 등 논의"
        }
      ]
    },
    {
      "term": "회담",
      "total": 4,
      "sourceCount": 3,
      "sources": [
        "yna",
        "donga",
        "khan"
      ],
      "examples": [
        {
          "source": "yna",
          "title": "韓美국방장관 워싱턴서 회담…전작권·핵잠·정보공유정상화 논의"
        },
        {
          "source": "yna",
          "title": "[속보] 한미 국방장관, 워싱턴서 회담 시작…전작권·핵잠협력 등 논의"
        },
        {
          "source": "donga",
          "title": "한미 국방장관, 워싱턴서 회담 돌입…전작권 전환 등 논의"
        }
      ]
    },
    {
      "term": "전작권",
      "total": 4,
      "sourceCount": 3,
      "sources": [
        "yna",
        "donga",
        "khan"
      ],
      "examples": [
        {
          "source": "yna",
          "title": "韓美국방장관 워싱턴서 회담…전작권·핵잠·정보공유정상화 논의"
        },
        {
          "source": "yna",
          "title": "[속보] 한미 국방장관, 워싱턴서 회담 시작…전작권·핵잠협력 등 논의"
        },
        {
          "source": "donga",
          "title": "한미 국방장관, 워싱턴서 회담 돌입…전작권 전환 등 논의"
        }
      ]
    },
    {
      "term": "흉기로",
      "total": 4,
      "sourceCount": 3,
      "sources": [
        "yna",
        "khan",
        "mk"
      ],
      "examples": [
        {
          "source": "yna",
          "title": "남극 장보고기지 대원, 흉기로 동료위협…국내 이송돼 경찰 수사"
        },
        {
          "source": "yna",
          "title": "층간소음 불만에 위층 주민 흉기로 살해한 20대 구속"
        },
        {
          "source": "khan",
          "title": "남극 장보고 과학기지서 흉기로 동료 위협한 대원 국내 이송···경찰 수사 착수"
        }
      ]
    },
    {
      "term": "경찰",
      "total": 4,
      "sourceCount": 3,
      "sources": [
        "yna",
        "khan",
        "mk"
      ],
      "examples": [
        {
          "source": "yna",
          "title": "남극 장보고기지 대원, 흉기로 동료위협…국내 이송돼 경찰 수사"
        },
        {
          "source": "yna",
          "title": "충남 계룡시장 출마 여야 후보, 잇따라 경찰 압수수색 받아"
        },
        {
          "source": "khan",
          "title": "남극 장보고 과학기지서 흉기로 동료 위협한 대원 국내 이송···경찰 수사 착수"
        }
      ]
    },
    {
      "term": "수사",
      "total": 4,
      "sourceCount": 3,
      "sources": [
        "yna",
        "khan",
        "mk"
      ],
      "examples": [
        {
          "source": "yna",
          "title": "남극 장보고기지 대원, 흉기로 동료위협…국내 이송돼 경찰 수사"
        },
        {
          "source": "yna",
          "title": "검찰, 백해룡 '세관 직원 명예훼손' 의혹 수사 착수"
        },
        {
          "source": "khan",
          "title": "남극 장보고 과학기지서 흉기로 동료 위협한 대원 국내 이송···경찰 수사 착수"
        }
      ]
    },
    {
      "term": "너무",
      "total": 4,
      "sourceCount": 3,
      "sources": [
        "yna",
        "donga",
        "mk"
      ],
      "examples": [
        {
          "source": "yna",
          "title": "\"너무 예의가 없네\"…케냐서 청중에 호통친 마크롱"
        },
        {
          "source": "yna",
          "title": "우상호 \"공약 파기 사과부터\" vs 김진태 \"현안 너무 모른다\""
        },
        {
          "source": "donga",
          "title": "강수지 “뛰는 사람 너무 부러워”…‘디스크 협착증’ 고충 토로"
        }
      ]
    },
    {
      "term": "입건",
      "total": 4,
      "sourceCount": 3,
      "sources": [
        "yna",
        "mk",
        "hani"
      ],
      "examples": [
        {
          "source": "yna",
          "title": "대전 공사장서 외국인 노동자 향해 둔기 휘두른 50대 입건"
        },
        {
          "source": "yna",
          "title": "여성 행세하며 '명품 헐값 판매' 사기…20억원 가로챈 남성 입건"
        },
        {
          "source": "mk",
          "title": "“북한에 원유 90만배럴 반출”…전한길 등 가짜뉴스 유포자 10명 입건"
        }
      ]
    },
    {
      "term": "방문",
      "total": 4,
      "sourceCount": 3,
      "sources": [
        "yna",
        "donga",
        "hani"
      ],
      "examples": [
        {
          "source": "yna",
          "title": "성평등장관, 광주 여고생 살인사건 현장 방문…\"대책 마련\""
        },
        {
          "source": "yna",
          "title": "아르노 LVMH 회장, 신세계·롯데 매장 방문…롯데선 신동빈 동행(종합)"
        },
        {
          "source": "donga",
          "title": "루이뷔통 아르노 회장 부녀, 신세계百 본점 방문"
        }
      ]
    },
    {
      "term": "전쟁",
      "total": 4,
      "sourceCount": 3,
      "sources": [
        "yna",
        "khan",
        "hani"
      ],
      "examples": [
        {
          "source": "yna",
          "title": "네타냐후 \"이란 우라늄 제거할 때까지 전쟁 안 끝나\"(종합)"
        },
        {
          "source": "yna",
          "title": "전쟁 변수에도 굳건한 우상혁 \"아시안게임, 해볼 만하다\""
        },
        {
          "source": "khan",
          "title": "전쟁 와중에도 1분기 주식 매도 개미 10명 중 8명 ‘이익’···최대 수익·손실 종목은?"
        }
      ]
    },
    {
      "term": "협상",
      "total": 4,
      "sourceCount": 3,
      "sources": [
        "yna",
        "khan",
        "mk"
      ],
      "examples": [
        {
          "source": "yna",
          "title": "우크라전 협상 중재자로 슈뢰더 띄운 푸틴…독일 정부는 일축"
        },
        {
          "source": "khan",
          "title": "삼성전자 노사, 사후조정 첫날 11시간 ‘마라톤 협상’…끝내 합의 불발"
        },
        {
          "source": "khan",
          "title": "수십 년 제재로 맷집 세진 이란, 협상 주도권 쥐고 ‘버티기 전술’"
        }
      ]
    },
    {
      "term": "조국",
      "total": 3,
      "sourceCount": 3,
      "sources": [
        "sbs",
        "yna",
        "mk"
      ],
      "examples": [
        {
          "source": "sbs",
          "title": "[지선직관] '1년 월세' 구한 조국…김용남 SNS에 \"인생 오점\""
        },
        {
          "source": "yna",
          "title": "혁신당, '조국 평택 단기 월세계약설'에 \"1년 계약해 거주 중\""
        },
        {
          "source": "mk",
          "title": "유의동 “조국, 평택에 뿌리내리겠다더니 월세 2개월만 계약?”"
        }
      ]
    },
    {
      "term": "시간",
      "total": 3,
      "sourceCount": 3,
      "sources": [
        "sbs",
        "yna",
        "khan"
      ],
      "examples": [
        {
          "source": "sbs",
          "title": "이 대통령 \"선호투표제, 결선투표 비용·시간 아끼기 위한 것\""
        },
        {
          "source": "yna",
          "title": "'연어 술파티' 박상용 대검서 6시간 징계심의…朴 \"충실히 소명\"(종합2보)"
        },
        {
          "source": "khan",
          "title": "삼성전자 노사, 사후조정 첫날 11시간 ‘마라톤 협상’…끝내 합의 불발"
        }
      ]
    },
    {
      "term": "지선",
      "total": 3,
      "sourceCount": 3,
      "sources": [
        "sbs",
        "donga",
        "khan"
      ],
      "examples": [
        {
          "source": "sbs",
          "title": "[여담야담] 이 대통령 \"3대 살해 위협서 국민이 살려주셔\"…야 \"공소취소 빼면 돼\" 여 \"지선 후 야당 의견도 수렴\""
        },
        {
          "source": "donga",
          "title": "英 스타머 총리, 지선 참패에 사퇴 거부…“물러나지 않는 것도 책임”"
        },
        {
          "source": "khan",
          "title": "[6·3 지선 격전지 민심 르포]“정부에 힘 줘야” “고초 치렀는데” “지역 출신 유일” 안갯속"
        }
      ]
    },
    {
      "term": "강력히",
      "total": 3,
      "sourceCount": 3,
      "sources": [
        "sbs",
        "mk",
        "hani"
      ],
      "examples": [
        {
          "source": "sbs",
          "title": "청와대 \"나무호 등 민간선박 공격 용납 안 돼…강력히 규탄\""
        },
        {
          "source": "mk",
          "title": "\"나무호 공격 강력히 규탄…공격 비행체 추가 조사할것\""
        },
        {
          "source": "hani",
          "title": "위성락 “나무호 공격 강력히 규탄”…잔해는 드론으로 확인"
        }
      ]
    },
    {
      "term": "확대",
      "total": 3,
      "sourceCount": 3,
      "sources": [
        "yna",
        "donga",
        "mk"
      ],
      "examples": [
        {
          "source": "yna",
          "title": "트럼프 \"해방 프로젝트 재개 검토\"…규모 확대 시사로 이란 압박"
        },
        {
          "source": "donga",
          "title": "‘미토스 쇼크’ 대비… 과기부, 앤스로픽과 협력 확대 나선다"
        },
        {
          "source": "mk",
          "title": "트럼프 “해방 프로젝트 재개 검토”…규모 확대 시사로 이란 압박"
        }
      ]
    },
    {
      "term": "주도",
      "total": 3,
      "sourceCount": 3,
      "sources": [
        "yna",
        "donga",
        "khan"
      ],
      "examples": [
        {
          "source": "yna",
          "title": "안규백 \"韓주도 한반도 방위 최선\"…헤그세스 \"美에 협력하길\"(종합)"
        },
        {
          "source": "donga",
          "title": "안규백 “韓 주도 한반도 방위” 헤그세스 “위협적 환경, 美와 함께 해야”"
        },
        {
          "source": "khan",
          "title": "‘삼전닉스’ 주도 성장, 이익 원청 독식은 ‘지속 가능성’에 한계···자원 재분배 논의를"
        }
      ]
    },
    {
      "term": "헤그세스",
      "total": 3,
      "sourceCount": 3,
      "sources": [
        "yna",
        "donga",
        "hani"
      ],
      "examples": [
        {
          "source": "yna",
          "title": "안규백 \"韓주도 한반도 방위 최선\"…헤그세스 \"美에 협력하길\"(종합)"
        },
        {
          "source": "donga",
          "title": "안규백 “韓 주도 한반도 방위” 헤그세스 “위협적 환경, 美와 함께 해야”"
        },
        {
          "source": "hani",
          "title": "한·미 국방 회담서 헤그세스 “어깨 나란히”…호르무즈 협력 주문했나"
        }
      ]
    },
    {
      "term": "주장",
      "total": 3,
      "sourceCount": 3,
      "sources": [
        "yna",
        "donga",
        "khan"
      ],
      "examples": [
        {
          "source": "yna",
          "title": "트럼프 참석행사 총격 용의자, 법정서 무죄 주장"
        },
        {
          "source": "donga",
          "title": "러·우, 3일 휴전에도 충돌 지속…서로 ‘합의 위반’ 주장"
        },
        {
          "source": "khan",
          "title": "‘트럼프 암살 시도’ 만찬장 총격 남성···재판에서 “무죄” 주장"
        }
      ]
    },
    {
      "term": "대원",
      "total": 3,
      "sourceCount": 3,
      "sources": [
        "yna",
        "khan",
        "mk"
      ],
      "examples": [
        {
          "source": "yna",
          "title": "남극 장보고기지 대원, 흉기로 동료위협…국내 이송돼 경찰 수사"
        },
        {
          "source": "khan",
          "title": "남극 장보고 과학기지서 흉기로 동료 위협한 대원 국내 이송···경찰 수사 착수"
        },
        {
          "source": "mk",
          "title": "흉기로 동료위협한 남극 장보고기지 대원…국내 이송돼 경찰 수사"
        }
      ]
    },
    {
      "term": "글로벌",
      "total": 3,
      "sourceCount": 3,
      "sources": [
        "yna",
        "donga",
        "mk"
      ],
      "examples": [
        {
          "source": "yna",
          "title": "강원대 평화학과, '길 위의 평화' 글로벌 플로깅 행사 개최"
        },
        {
          "source": "donga",
          "title": "“생큐 트럼프” 이란戰 유가급등에 글로벌 원유업계 깜짝 실적"
        },
        {
          "source": "mk",
          "title": "구글 vs 메타 vs 오픈AI … 글로벌 AI로봇, 숨가쁜 OS 경쟁"
        }
      ]
    },
    {
      "term": "협력",
      "total": 3,
      "sourceCount": 3,
      "sources": [
        "yna",
        "donga",
        "hani"
      ],
      "examples": [
        {
          "source": "yna",
          "title": "조현, 중앙아 5개국 대사와 정상회의 협력 논의"
        },
        {
          "source": "donga",
          "title": "‘미토스 쇼크’ 대비… 과기부, 앤스로픽과 협력 확대 나선다"
        },
        {
          "source": "hani",
          "title": "한·미 국방 회담서 헤그세스 “어깨 나란히”…호르무즈 협력 주문했나"
        }
      ]
    },
    {
      "term": "전국",
      "total": 3,
      "sourceCount": 3,
      "sources": [
        "yna",
        "donga",
        "hani"
      ],
      "examples": [
        {
          "source": "yna",
          "title": "[날씨] 내일도 전국 곳곳 비…전라 최대 70㎜"
        },
        {
          "source": "donga",
          "title": "[오늘날씨]“출근길 우산 챙기세요”…전국 대부분 비, 돌풍·우박도"
        },
        {
          "source": "hani",
          "title": "경희대, ‘제27회 총장배 전국 중·고등학생 골프대회’ 개최 “경기가 끝나도 성장은 계속된다”"
        }
      ]
    },
    {
      "term": "여성",
      "total": 3,
      "sourceCount": 3,
      "sources": [
        "yna",
        "khan",
        "mk"
      ],
      "examples": [
        {
          "source": "yna",
          "title": "여성 행세하며 '명품 헐값 판매' 사기…20억원 가로챈 남성 입건"
        },
        {
          "source": "khan",
          "title": "“멈추지 않는 여성 폭력…10년 전 강남역, 어디에나 있다”"
        },
        {
          "source": "mk",
          "title": "“명품 헐값에 판다더니”…여성 인플루언서 행세하며 20억 가로챈 20대 남자"
        }
      ]
    },
    {
      "term": "명품",
      "total": 3,
      "sourceCount": 3,
      "sources": [
        "yna",
        "mk",
        "hani"
      ],
      "examples": [
        {
          "source": "yna",
          "title": "여성 행세하며 '명품 헐값 판매' 사기…20억원 가로챈 남성 입건"
        },
        {
          "source": "mk",
          "title": "“명품 헐값에 판다더니”…여성 인플루언서 행세하며 20억 가로챈 20대 남자"
        },
        {
          "source": "hani",
          "title": "여성인척 명품 헐값에 판다며 20억 뜯어내…20대 남성 입건"
        }
      ]
    },
    {
      "term": "조사",
      "total": 3,
      "sourceCount": 3,
      "sources": [
        "yna",
        "khan",
        "mk"
      ],
      "examples": [
        {
          "source": "yna",
          "title": "공격주체 규명 '스모킹건' 엔진잔해 조사…어떻게 이뤄지나"
        },
        {
          "source": "khan",
          "title": "공수처, ‘룸살롱 접대 의혹’ 지귀연 조사"
        },
        {
          "source": "mk",
          "title": "초등학생들 무더기 구토·발열…대전 초교 집단 증상 조사"
        }
      ]
    },
    {
      "term": "삼성",
      "total": 3,
      "sourceCount": 3,
      "sources": [
        "yna",
        "donga",
        "mk"
      ],
      "examples": [
        {
          "source": "yna",
          "title": "[AI픽] 국가 AI컴퓨팅센터 시동…삼성SDS 맡는다"
        },
        {
          "source": "donga",
          "title": "삼성SDS 컨소시엄, ‘국가 AI컴퓨팅 센터’ 만든다"
        },
        {
          "source": "mk",
          "title": "매경증권대상 NH투자證 … 퇴직연금 대상에 삼성證"
        }
      ]
    },
    {
      "term": "영업익",
      "total": 3,
      "sourceCount": 3,
      "sources": [
        "yna",
        "donga",
        "khan"
      ],
      "examples": [
        {
          "source": "yna",
          "title": "롯데케미칼 1분기 영업익 735억원…\"실적 개선세 지속\"(종합2보)"
        },
        {
          "source": "donga",
          "title": "백화점 외국인 매출 늘자… 롯데쇼핑 1분기 영업익 71% 껑충"
        },
        {
          "source": "khan",
          "title": "에쓰오일, 고유가·재고효과에 1분기 1조 영업익"
        }
      ]
    },
    {
      "term": "지속",
      "total": 3,
      "sourceCount": 3,
      "sources": [
        "yna",
        "donga",
        "khan"
      ],
      "examples": [
        {
          "source": "yna",
          "title": "롯데케미칼 1분기 영업익 735억원…\"실적 개선세 지속\"(종합2보)"
        },
        {
          "source": "donga",
          "title": "러·우, 3일 휴전에도 충돌 지속…서로 ‘합의 위반’ 주장"
        },
        {
          "source": "khan",
          "title": "‘삼전닉스’ 주도 성장, 이익 원청 독식은 ‘지속 가능성’에 한계···자원 재분배 논의를"
        }
      ]
    },
    {
      "term": "수익",
      "total": 3,
      "sourceCount": 3,
      "sources": [
        "donga",
        "khan",
        "hani"
      ],
      "examples": [
        {
          "source": "donga",
          "title": "1분기 개인투자자 80%가 수익… 평균 848만원"
        },
        {
          "source": "khan",
          "title": "전쟁 와중에도 1분기 주식 매도 개미 10명 중 8명 ‘이익’···최대 수익·손실 종목은?"
        },
        {
          "source": "hani",
          "title": "내 수익 5천만원 넘었나?…금투세 재점화에도 정부·여당 선 긋기"
        }
      ]
    },
    {
      "term": "청와대",
      "total": 6,
      "sourceCount": 2,
      "sources": [
        "sbs",
        "hani"
      ],
      "examples": [
        {
          "source": "sbs",
          "title": "청와대 \"민간 선박 공격 규탄\"…대상은 특정 안 해"
        },
        {
          "source": "sbs",
          "title": "청와대 \"나무호 공격 규탄\"…이란 관련성엔 \"미지 영역\""
        },
        {
          "source": "sbs",
          "title": "청와대 \"나무호 등 공격 강력 규탄…안전보장 국제노력 동참\""
        }
      ]
    },
    {
      "term": "휴전",
      "total": 5,
      "sourceCount": 2,
      "sources": [
        "yna",
        "mk"
      ],
      "examples": [
        {
          "source": "yna",
          "title": "트럼프 \"이란과의 휴전 간신히 유지…해방 프로젝트 재개 검토\"(종합)"
        },
        {
          "source": "yna",
          "title": "트럼프 \"휴전 유지되고 있지만 가장 약한 상태…연명장치 의존\""
        },
        {
          "source": "yna",
          "title": "[속보] 트럼프 \"이란전 휴전 가장 약한 상태…연명장치 의존\""
        }
      ]
    },
    {
      "term": "제재",
      "total": 5,
      "sourceCount": 2,
      "sources": [
        "yna",
        "khan"
      ],
      "examples": [
        {
          "source": "yna",
          "title": "EU, '요르단강 서안 폭력' 이스라엘 정착민 제재 합의(종합)"
        },
        {
          "source": "yna",
          "title": "EU, '서안지구 폭력' 이스라엘 정착민 제재 합의"
        },
        {
          "source": "yna",
          "title": "EU, 우크라 아동 강제이주 관여 러 개인 16명·기관 7곳 제재"
        }
      ]
    },
    {
      "term": "우크라",
      "total": 5,
      "sourceCount": 2,
      "sources": [
        "yna",
        "mk"
      ],
      "examples": [
        {
          "source": "yna",
          "title": "EU, 우크라 아동 강제이주 관여 러 개인 16명·기관 7곳 제재"
        },
        {
          "source": "yna",
          "title": "러·우크라, 또 휴전 공방…합의 위반 '네탓'(종합)"
        },
        {
          "source": "yna",
          "title": "라트비아 국방장관 날린 우크라 드론…영공침범에 사임"
        }
      ]
    },
    {
      "term": "초등생",
      "total": 5,
      "sourceCount": 2,
      "sources": [
        "yna",
        "mk"
      ],
      "examples": [
        {
          "source": "yna",
          "title": "인천 아파트 단지서 60대 남성이 초등생 강제추행"
        },
        {
          "source": "yna",
          "title": "청송 주왕산서 초등생 실종 이틀째…야간에도 샅샅이 수색한다(종합)"
        },
        {
          "source": "yna",
          "title": "주왕산서 초등생 실종 이틀째…야간에도 샅샅이 수색한다"
        }
      ]
    },
    {
      "term": "사설",
      "total": 5,
      "sourceCount": 2,
      "sources": [
        "donga",
        "hani"
      ],
      "examples": [
        {
          "source": "donga",
          "title": "[사설]나무호 피격 확인… 호르무즈에 갇힌 26척 안전이 최우선"
        },
        {
          "source": "donga",
          "title": "[사설]“명륜당, 정책자금 빌려 가맹점에 고리대부”… 일벌백계해야"
        },
        {
          "source": "donga",
          "title": "[사설]전기차 100만 시대인데, ‘충전 낭인’에 ‘길막 시비’까지"
        }
      ]
    },
    {
      "term": "대통령",
      "total": 4,
      "sourceCount": 2,
      "sources": [
        "sbs",
        "khan"
      ],
      "examples": [
        {
          "source": "sbs",
          "title": "\"갭투자 허용 주장은 '억까'\"…이 대통령 SNS로 반박"
        },
        {
          "source": "sbs",
          "title": "이 대통령 \"선호투표제, 결선투표 비용·시간 아끼기 위한 것\""
        },
        {
          "source": "sbs",
          "title": "[여담야담] 이 대통령 \"3대 살해 위협서 국민이 살려주셔\"…야 \"공소취소 빼면 돼\" 여 \"지선 후 야당 의견도 수렴\""
        }
      ]
    },
    {
      "term": "방중",
      "total": 4,
      "sourceCount": 2,
      "sources": [
        "yna",
        "mk"
      ],
      "examples": [
        {
          "source": "yna",
          "title": "트럼프 방중 수행단에 테슬라·애플 CEO 합류…엔비디아는 빠져"
        },
        {
          "source": "yna",
          "title": "中, 트럼프 방중 앞두고 미중협력 강조한 '평화공존' 숏폼 공개"
        },
        {
          "source": "yna",
          "title": "中, 트럼프 방중 앞두고 美와 마약 사건 공조 부각…5명 체포"
        }
      ]
    },
    {
      "term": "규모",
      "total": 4,
      "sourceCount": 2,
      "sources": [
        "yna",
        "mk"
      ],
      "examples": [
        {
          "source": "yna",
          "title": "트럼프 \"해방 프로젝트 재개 검토\"…규모 확대 시사로 이란 압박"
        },
        {
          "source": "mk",
          "title": "트럼프 “해방 프로젝트 재개 검토”…규모 확대 시사로 이란 압박"
        },
        {
          "source": "mk",
          "title": "대성하이텍, 100억 원 규모 전환사채 발행"
        }
      ]
    },
    {
      "term": "외국인",
      "total": 4,
      "sourceCount": 2,
      "sources": [
        "yna",
        "donga"
      ],
      "examples": [
        {
          "source": "yna",
          "title": "대전 공사장서 외국인 노동자 향해 둔기 휘두른 50대 입건"
        },
        {
          "source": "yna",
          "title": "[울산소식] 동구 외국인 봉사자 '클린 홍보단'…쓰레기 무단투기 대응"
        },
        {
          "source": "donga",
          "title": "카드에 K팝 입히니 발급 2배… 외국인 공략 나선 K금융"
        }
      ]
    },
    {
      "term": "인천",
      "total": 4,
      "sourceCount": 2,
      "sources": [
        "yna",
        "mk"
      ],
      "examples": [
        {
          "source": "yna",
          "title": "인천 아파트 단지서 60대 남성이 초등생 강제추행"
        },
        {
          "source": "yna",
          "title": "인천 옹진에 호우주의보 해제"
        },
        {
          "source": "yna",
          "title": "인천 옹진에 호우주의보"
        }
      ]
    },
    {
      "term": "갭투자",
      "total": 3,
      "sourceCount": 2,
      "sources": [
        "sbs",
        "khan"
      ],
      "examples": [
        {
          "source": "sbs",
          "title": "\"세 준 1주택 매도 기회에 '갭투자 허용'?…'억까'\""
        },
        {
          "source": "sbs",
          "title": "\"갭투자 허용 주장은 '억까'\"…이 대통령 SNS로 반박"
        },
        {
          "source": "khan",
          "title": "이 대통령 “세 낀 집 무주택 매수자 실거주 유예가 갭투자 허용? 억지 비난”"
        }
      ]
    },
    {
      "term": "허용",
      "total": 3,
      "sourceCount": 2,
      "sources": [
        "sbs",
        "khan"
      ],
      "examples": [
        {
          "source": "sbs",
          "title": "\"세 준 1주택 매도 기회에 '갭투자 허용'?…'억까'\""
        },
        {
          "source": "sbs",
          "title": "\"갭투자 허용 주장은 '억까'\"…이 대통령 SNS로 반박"
        },
        {
          "source": "khan",
          "title": "이 대통령 “세 낀 집 무주택 매수자 실거주 유예가 갭투자 허용? 억지 비난”"
        }
      ]
    },
    {
      "term": "강력",
      "total": 3,
      "sourceCount": 2,
      "sources": [
        "sbs",
        "hani"
      ],
      "examples": [
        {
          "source": "sbs",
          "title": "청와대 \"나무호 등 공격 강력 규탄…안전보장 국제노력 동참\""
        },
        {
          "source": "sbs",
          "title": "청와대 \"나무호 등 민간선박 공격 용납 안 돼…강력 규탄\""
        },
        {
          "source": "hani",
          "title": "청와대 “나무호 피격, 강력 규탄”…프랑스·중국처럼 특정은 안 해"
        }
      ]
    },
    {
      "term": "마련",
      "total": 3,
      "sourceCount": 2,
      "sources": [
        "sbs",
        "yna"
      ],
      "examples": [
        {
          "source": "sbs",
          "title": "강훈식, '고교생 살해'에 \"가볍게 여겨선 안돼…특단 대책 마련\""
        },
        {
          "source": "yna",
          "title": "성평등장관, 광주 여고생 살인사건 현장 방문…\"대책 마련\""
        },
        {
          "source": "yna",
          "title": "대법, 중대재해법 양형기준 신설한다…응급의료방해 기준도 마련"
        }
      ]
    },
    {
      "term": "후보",
      "total": 3,
      "sourceCount": 2,
      "sources": [
        "sbs",
        "yna"
      ],
      "examples": [
        {
          "source": "sbs",
          "title": "[여담야담] 장동혁, 또 계엄 옹호 논란 발언…주광덕 \"2선 후퇴 안 하면 후보 등록 안 해\""
        },
        {
          "source": "yna",
          "title": "충남 계룡시장 출마 여야 후보, 잇따라 경찰 압수수색 받아"
        },
        {
          "source": "yna",
          "title": "'측근 정치자금 감찰' 민주당 손훈모 순천시장 후보 자격 유지"
        }
      ]
    },
    {
      "term": "한타바이러스",
      "total": 3,
      "sourceCount": 2,
      "sources": [
        "yna",
        "khan"
      ],
      "examples": [
        {
          "source": "yna",
          "title": "한타바이러스 크루즈선 탑승 프랑스인 1명 확진(종합)"
        },
        {
          "source": "yna",
          "title": "크루즈선 덮친 한타바이러스 확진 총 7명으로 늘어"
        },
        {
          "source": "khan",
          "title": "‘한타바이러스 크루즈선’ 승객 귀국길…일부 ‘확진’"
        }
      ]
    },
    {
      "term": "크루즈선",
      "total": 3,
      "sourceCount": 2,
      "sources": [
        "yna",
        "khan"
      ],
      "examples": [
        {
          "source": "yna",
          "title": "한타바이러스 크루즈선 탑승 프랑스인 1명 확진(종합)"
        },
        {
          "source": "yna",
          "title": "크루즈선 덮친 한타바이러스 확진 총 7명으로 늘어"
        },
        {
          "source": "khan",
          "title": "‘한타바이러스 크루즈선’ 승객 귀국길…일부 ‘확진’"
        }
      ]
    },
    {
      "term": "확진",
      "total": 3,
      "sourceCount": 2,
      "sources": [
        "yna",
        "khan"
      ],
      "examples": [
        {
          "source": "yna",
          "title": "한타바이러스 크루즈선 탑승 프랑스인 1명 확진(종합)"
        },
        {
          "source": "yna",
          "title": "크루즈선 덮친 한타바이러스 확진 총 7명으로 늘어"
        },
        {
          "source": "khan",
          "title": "‘한타바이러스 크루즈선’ 승객 귀국길…일부 ‘확진’"
        }
      ]
    },
    {
      "term": "스타머",
      "total": 3,
      "sourceCount": 2,
      "sources": [
        "yna",
        "donga"
      ],
      "examples": [
        {
          "source": "yna",
          "title": "지방선거 참패 후폭풍…노동당 내 반란 직면한 스타머"
        },
        {
          "source": "yna",
          "title": "'지방선거 참패' 스타머, 사임 압박 거부…영국 국채금리 상승"
        },
        {
          "source": "donga",
          "title": "英 스타머 총리, 지선 참패에 사퇴 거부…“물러나지 않는 것도 책임”"
        }
      ]
    },
    {
      "term": "안규백",
      "total": 3,
      "sourceCount": 2,
      "sources": [
        "yna",
        "donga"
      ],
      "examples": [
        {
          "source": "yna",
          "title": "안규백 \"韓주도 한반도 방위 최선\"…헤그세스 \"美에 협력하길\"(종합)"
        },
        {
          "source": "yna",
          "title": "[속보] 안규백 국방 \"한국주도의 한반도 방위 실현에 최선\""
        },
        {
          "source": "donga",
          "title": "안규백 “韓 주도 한반도 방위” 헤그세스 “위협적 환경, 美와 함께 해야”"
        }
      ]
    },
    {
      "term": "한반도",
      "total": 3,
      "sourceCount": 2,
      "sources": [
        "yna",
        "donga"
      ],
      "examples": [
        {
          "source": "yna",
          "title": "안규백 \"韓주도 한반도 방위 최선\"…헤그세스 \"美에 협력하길\"(종합)"
        },
        {
          "source": "yna",
          "title": "[속보] 안규백 국방 \"한국주도의 한반도 방위 실현에 최선\""
        },
        {
          "source": "donga",
          "title": "안규백 “韓 주도 한반도 방위” 헤그세스 “위협적 환경, 美와 함께 해야”"
        }
      ]
    },
    {
      "term": "방위",
      "total": 3,
      "sourceCount": 2,
      "sources": [
        "yna",
        "donga"
      ],
      "examples": [
        {
          "source": "yna",
          "title": "안규백 \"韓주도 한반도 방위 최선\"…헤그세스 \"美에 협력하길\"(종합)"
        },
        {
          "source": "yna",
          "title": "[속보] 안규백 국방 \"한국주도의 한반도 방위 실현에 최선\""
        },
        {
          "source": "donga",
          "title": "안규백 “韓 주도 한반도 방위” 헤그세스 “위협적 환경, 美와 함께 해야”"
        }
      ]
    },
    {
      "term": "국가",
      "total": 3,
      "sourceCount": 2,
      "sources": [
        "yna",
        "donga"
      ],
      "examples": [
        {
          "source": "yna",
          "title": "아동권리보장원 명칭 앞에 '국가' 붙인다…\"책임성 강화\""
        },
        {
          "source": "yna",
          "title": "[AI픽] 국가 AI컴퓨팅센터 시동…삼성SDS 맡는다"
        },
        {
          "source": "donga",
          "title": "삼성SDS 컨소시엄, ‘국가 AI컴퓨팅 센터’ 만든다"
        }
      ]
    },
    {
      "term": "국방",
      "total": 3,
      "sourceCount": 2,
      "sources": [
        "yna",
        "hani"
      ],
      "examples": [
        {
          "source": "yna",
          "title": "[속보] 안규백 국방 \"한국주도의 한반도 방위 실현에 최선\""
        },
        {
          "source": "yna",
          "title": "[속보] 美국방, 이란전 거론하며 \"파트너들이 어깨 나란히 해주길\""
        },
        {
          "source": "hani",
          "title": "한·미 국방 회담서 헤그세스 “어깨 나란히”…호르무즈 협력 주문했나"
        }
      ]
    },
    {
      "term": "폭력",
      "total": 3,
      "sourceCount": 2,
      "sources": [
        "yna",
        "khan"
      ],
      "examples": [
        {
          "source": "yna",
          "title": "EU, '요르단강 서안 폭력' 이스라엘 정착민 제재 합의(종합)"
        },
        {
          "source": "yna",
          "title": "EU, '서안지구 폭력' 이스라엘 정착민 제재 합의"
        },
        {
          "source": "khan",
          "title": "“멈추지 않는 여성 폭력…10년 전 강남역, 어디에나 있다”"
        }
      ]
    },
    {
      "term": "소명",
      "total": 3,
      "sourceCount": 2,
      "sources": [
        "yna",
        "hani"
      ],
      "examples": [
        {
          "source": "yna",
          "title": "'연어 술파티' 박상용 대검서 6시간 징계심의…朴 \"충실히 소명\"(종합2보)"
        },
        {
          "source": "yna",
          "title": "대검 감찰위, '연어 술파티' 박상용 징계심의…朴 \"충실히 소명\"(종합)"
        },
        {
          "source": "hani",
          "title": "‘회유 의혹’ 박상용 검사, 감찰위 소명 뒤 “기회 감사”"
        }
      ]
    },
    {
      "term": "중국",
      "total": 3,
      "sourceCount": 2,
      "sources": [
        "yna",
        "mk"
      ],
      "examples": [
        {
          "source": "yna",
          "title": "중국 화물우주선 톈저우 10호, 우주정거장 도킹 성공"
        },
        {
          "source": "yna",
          "title": "대만 WHO 총회 참가 10년째 불발…中 \"하나의 중국 재증명\""
        },
        {
          "source": "mk",
          "title": "“태평양은 둘이 함께 쓰기 충분”…중국, 트럼프 방중 앞두고 공개한 영상 보니"
        }
      ]
    },
    {
      "term": "이송",
      "total": 3,
      "sourceCount": 2,
      "sources": [
        "yna",
        "khan"
      ],
      "examples": [
        {
          "source": "yna",
          "title": "김제 주택에서 불…80대 주민 연기흡입 이송"
        },
        {
          "source": "khan",
          "title": "남극 장보고 과학기지서 흉기로 동료 위협한 대원 국내 이송···경찰 수사 착수"
        },
        {
          "source": "khan",
          "title": "‘투옥’ 이란 노벨 평화상 모하마디, 병세 악화…보석 후 병원 이송"
        }
      ]
    },
    {
      "term": "아파트",
      "total": 3,
      "sourceCount": 2,
      "sources": [
        "yna",
        "mk"
      ],
      "examples": [
        {
          "source": "yna",
          "title": "인천 아파트 단지서 60대 남성이 초등생 강제추행"
        },
        {
          "source": "yna",
          "title": "'고객 차량 아파트 무단주차' 공항 주차대행업체 대표 약식기소"
        },
        {
          "source": "mk",
          "title": "인천 아파트 단지서 초등생 강제추행 한 60대 남성"
        }
      ]
    },
    {
      "term": "날씨",
      "total": 3,
      "sourceCount": 2,
      "sources": [
        "yna",
        "khan"
      ],
      "examples": [
        {
          "source": "yna",
          "title": "[날씨] 내일도 전국 곳곳 비…전라 최대 70㎜"
        },
        {
          "source": "khan",
          "title": "더워지는 날씨, 급변하는 트렌드에 제주 감귤 ‘신품종 개발’ 속도 낸다"
        },
        {
          "source": "khan",
          "title": "[2026년 05월 12일 날씨]오락가락 비 그치고 나면 기온 올라"
        }
      ]
    },
    {
      "term": "앞두고",
      "total": 3,
      "sourceCount": 2,
      "sources": [
        "yna",
        "mk"
      ],
      "examples": [
        {
          "source": "yna",
          "title": "中, 트럼프 방중 앞두고 미중협력 강조한 '평화공존' 숏폼 공개"
        },
        {
          "source": "yna",
          "title": "中, 트럼프 방중 앞두고 美와 마약 사건 공조 부각…5명 체포"
        },
        {
          "source": "mk",
          "title": "“태평양은 둘이 함께 쓰기 충분”…중국, 트럼프 방중 앞두고 공개한 영상 보니"
        }
      ]
    },
    {
      "term": "가로챈",
      "total": 3,
      "sourceCount": 2,
      "sources": [
        "yna",
        "mk"
      ],
      "examples": [
        {
          "source": "yna",
          "title": "여성 행세하며 '명품 헐값 판매' 사기…20억원 가로챈 남성 입건"
        },
        {
          "source": "yna",
          "title": "온라인 중고거래 사기로 7천만원 가로챈 30대 구속영장"
        },
        {
          "source": "mk",
          "title": "“명품 헐값에 판다더니”…여성 인플루언서 행세하며 20억 가로챈 20대 남자"
        }
      ]
    },
    {
      "term": "인재양성",
      "total": 3,
      "sourceCount": 2,
      "sources": [
        "yna",
        "hani"
      ],
      "examples": [
        {
          "source": "yna",
          "title": "[과학스냅] KIST·서울시립대, 미래 수소융합 공동연구·인재양성 협업"
        },
        {
          "source": "hani",
          "title": "서울과기대, 산업통상부 인재양성 사업 선정… AX 기반 온디바이스 AI 전문 인력 키운다"
        },
        {
          "source": "hani",
          "title": "덕성여대-인실리코젠, 바이오 빅데이터 기반 AI 인재양성 협약체결"
        }
      ]
    },
    {
      "term": "주왕산서",
      "total": 3,
      "sourceCount": 2,
      "sources": [
        "yna",
        "mk"
      ],
      "examples": [
        {
          "source": "yna",
          "title": "청송 주왕산서 초등생 실종 이틀째…야간에도 샅샅이 수색한다(종합)"
        },
        {
          "source": "yna",
          "title": "주왕산서 초등생 실종 이틀째…야간에도 샅샅이 수색한다"
        },
        {
          "source": "mk",
          "title": "“금방 돌아올 줄 알았는데”…주왕산서 사라진 초등생, 야간 수색 돌입"
        }
      ]
    },
    {
      "term": "혐의",
      "total": 3,
      "sourceCount": 2,
      "sources": [
        "yna",
        "khan"
      ],
      "examples": [
        {
          "source": "yna",
          "title": "강진원 전남 강진군수, 성추행 혐의 고발 당해"
        },
        {
          "source": "yna",
          "title": "국조실 직원, 식당 업무방해 혐의 받아…\"직위해제 등 엄정조치\""
        },
        {
          "source": "khan",
          "title": "여고생 살해범, 범행 하루 전 ‘성범죄 혐의’로 고소당해"
        }
      ]
    }
  ],
  "singleSourceTop": [
    {
      "term": "여담야담",
      "total": 3,
      "sourceCount": 1,
      "sources": [
        "sbs"
      ],
      "examples": [
        {
          "source": "sbs",
          "title": "[여담야담] 이 대통령 \"3대 살해 위협서 국민이 살려주셔\"…야 \"공소취소 빼면 돼\" 여 \"지선 후 야당 의견도 수렴\""
        },
        {
          "source": "sbs",
          "title": "[여담야담] 장동혁, 또 계엄 옹호 논란 발언…주광덕 \"2선 후퇴 안 하면 후보 등록 안 해\""
        },
        {
          "source": "sbs",
          "title": "[여담야담] 세 대결 뒤 '단일화' 미묘한 변화?…한동훈 \"세상에 절대 안 되는 것 없어\""
        }
      ]
    },
    {
      "term": "의존",
      "total": 3,
      "sourceCount": 1,
      "sources": [
        "yna"
      ],
      "examples": [
        {
          "source": "yna",
          "title": "트럼프 \"휴전 유지되고 있지만 가장 약한 상태…연명장치 의존\""
        },
        {
          "source": "yna",
          "title": "[속보] 트럼프 \"이란전 휴전 가장 약한 상태…연명장치 의존\""
        },
        {
          "source": "yna",
          "title": "16년 만의 정권교체 헝가리…\"러시아에 의존 안 할 것\""
        }
      ]
    },
    {
      "term": "압수수색",
      "total": 3,
      "sourceCount": 1,
      "sources": [
        "yna"
      ],
      "examples": [
        {
          "source": "yna",
          "title": "특검, '심우정 내란가담' 대검 압수수색…헌법존중TF 자료 확보(종합)"
        },
        {
          "source": "yna",
          "title": "\"압수수색 책잡히면 안 돼\"…전재수 보좌진, 망치로 PC 파손"
        },
        {
          "source": "yna",
          "title": "충남 계룡시장 출마 여야 후보, 잇따라 경찰 압수수색 받아"
        }
      ]
    },
    {
      "term": "애프터마켓서",
      "total": 3,
      "sourceCount": 1,
      "sources": [
        "yna"
      ],
      "examples": [
        {
          "source": "yna",
          "title": "펨트론, 애프터마켓서 10%대 급등"
        },
        {
          "source": "yna",
          "title": "지씨셀, 애프터마켓서 11%대 급등"
        },
        {
          "source": "yna",
          "title": "한샘, 애프터마켓서 12%대 급등"
        }
      ]
    },
    {
      "term": "급등",
      "total": 3,
      "sourceCount": 1,
      "sources": [
        "yna"
      ],
      "examples": [
        {
          "source": "yna",
          "title": "펨트론, 애프터마켓서 10%대 급등"
        },
        {
          "source": "yna",
          "title": "지씨셀, 애프터마켓서 11%대 급등"
        },
        {
          "source": "yna",
          "title": "한샘, 애프터마켓서 12%대 급등"
        }
      ]
    },
    {
      "term": "억까",
      "total": 2,
      "sourceCount": 1,
      "sources": [
        "sbs"
      ],
      "examples": [
        {
          "source": "sbs",
          "title": "\"세 준 1주택 매도 기회에 '갭투자 허용'?…'억까'\""
        },
        {
          "source": "sbs",
          "title": "\"갭투자 허용 주장은 '억까'\"…이 대통령 SNS로 반박"
        }
      ]
    },
    {
      "term": "일부러",
      "total": 2,
      "sourceCount": 1,
      "sources": [
        "sbs"
      ],
      "examples": [
        {
          "source": "sbs",
          "title": "일부러 기관실 노렸나…자폭 드론? 대함 미사일?"
        },
        {
          "source": "sbs",
          "title": "태국 화물선도 같은 곳 '뻥'…일부러 노리고 타격했나"
        }
      ]
    },
    {
      "term": "공소취소",
      "total": 2,
      "sourceCount": 1,
      "sources": [
        "sbs"
      ],
      "examples": [
        {
          "source": "sbs",
          "title": "\"내란 극복\" vs \"공소취소 막아야\"…승부처 된 '영남'"
        },
        {
          "source": "sbs",
          "title": "[여담야담] 이 대통령 \"3대 살해 위협서 국민이 살려주셔\"…야 \"공소취소 빼면 돼\" 여 \"지선 후 야당 의견도 수렴\""
        }
      ]
    },
    {
      "term": "강원",
      "total": 2,
      "sourceCount": 1,
      "sources": [
        "sbs"
      ],
      "examples": [
        {
          "source": "sbs",
          "title": "민주, 서울·강원 공천자대회…\"거센 파란 바람 불어 탈환해야\""
        },
        {
          "source": "sbs",
          "title": "정청래 \"강원 발전 약속\"…장동혁 \"선거 통해 정권 심판\""
        }
      ]
    },
    {
      "term": "살해",
      "total": 2,
      "sourceCount": 1,
      "sources": [
        "sbs"
      ],
      "examples": [
        {
          "source": "sbs",
          "title": "강훈식, '고교생 살해'에 \"가볍게 여겨선 안돼…특단 대책 마련\""
        },
        {
          "source": "sbs",
          "title": "[여담야담] 이 대통령 \"3대 살해 위협서 국민이 살려주셔\"…야 \"공소취소 빼면 돼\" 여 \"지선 후 야당 의견도 수렴\""
        }
      ]
    },
    {
      "term": "민간선박",
      "total": 2,
      "sourceCount": 1,
      "sources": [
        "sbs"
      ],
      "examples": [
        {
          "source": "sbs",
          "title": "청와대 \"나무호 등 민간선박 공격 용납 안 돼…강력 규탄\""
        },
        {
          "source": "sbs",
          "title": "청와대 \"나무호 등 민간선박 공격 용납 안 돼…강력히 규탄\""
        }
      ]
    },
    {
      "term": "용납",
      "total": 2,
      "sourceCount": 1,
      "sources": [
        "sbs"
      ],
      "examples": [
        {
          "source": "sbs",
          "title": "청와대 \"나무호 등 민간선박 공격 용납 안 돼…강력 규탄\""
        },
        {
          "source": "sbs",
          "title": "청와대 \"나무호 등 민간선박 공격 용납 안 돼…강력히 규탄\""
        }
      ]
    },
    {
      "term": "장동혁",
      "total": 2,
      "sourceCount": 1,
      "sources": [
        "sbs"
      ],
      "examples": [
        {
          "source": "sbs",
          "title": "[여담야담] 장동혁, 또 계엄 옹호 논란 발언…주광덕 \"2선 후퇴 안 하면 후보 등록 안 해\""
        },
        {
          "source": "sbs",
          "title": "정청래 \"강원 발전 약속\"…장동혁 \"선거 통해 정권 심판\""
        }
      ]
    },
    {
      "term": "한동훈",
      "total": 2,
      "sourceCount": 1,
      "sources": [
        "sbs"
      ],
      "examples": [
        {
          "source": "sbs",
          "title": "[여담야담] 세 대결 뒤 '단일화' 미묘한 변화?…한동훈 \"세상에 절대 안 되는 것 없어\""
        },
        {
          "source": "sbs",
          "title": "촬영 기자 발 헛디뎌 떨어지는데…한동훈 '무신경' 논란 영상 보니 [자막뉴스]"
        }
      ]
    },
    {
      "term": "정청래",
      "total": 2,
      "sourceCount": 1,
      "sources": [
        "sbs"
      ],
      "examples": [
        {
          "source": "sbs",
          "title": "[인터뷰] 송영길 \"정청래 칭찬해주고 싶다. 장동혁과 비교돼\"…이유는?"
        },
        {
          "source": "sbs",
          "title": "정청래 \"강원 발전 약속\"…장동혁 \"선거 통해 정권 심판\""
        }
      ]
    },
    {
      "term": "발전",
      "total": 2,
      "sourceCount": 1,
      "sources": [
        "sbs"
      ],
      "examples": [
        {
          "source": "sbs",
          "title": "민주, 강원도에서 선대위 첫 회의…\"도민 눈 번쩍 뜨일 발전 약속\""
        },
        {
          "source": "sbs",
          "title": "정청래 \"강원 발전 약속\"…장동혁 \"선거 통해 정권 심판\""
        }
      ]
    },
    {
      "term": "약속",
      "total": 2,
      "sourceCount": 1,
      "sources": [
        "sbs"
      ],
      "examples": [
        {
          "source": "sbs",
          "title": "민주, 강원도에서 선대위 첫 회의…\"도민 눈 번쩍 뜨일 발전 약속\""
        },
        {
          "source": "sbs",
          "title": "정청래 \"강원 발전 약속\"…장동혁 \"선거 통해 정권 심판\""
        }
      ]
    },
    {
      "term": "유지",
      "total": 2,
      "sourceCount": 1,
      "sources": [
        "yna"
      ],
      "examples": [
        {
          "source": "yna",
          "title": "트럼프 \"이란과의 휴전 간신히 유지…해방 프로젝트 재개 검토\"(종합)"
        },
        {
          "source": "yna",
          "title": "'측근 정치자금 감찰' 민주당 손훈모 순천시장 후보 자격 유지"
        }
      ]
    },
    {
      "term": "추진",
      "total": 2,
      "sourceCount": 1,
      "sources": [
        "yna"
      ],
      "examples": [
        {
          "source": "yna",
          "title": "英, '마지막 제철 용광로' 브리티시스틸 국유화 추진"
        },
        {
          "source": "yna",
          "title": "나토 회원국 리투아니아, 호르무즈 파병 추진"
        }
      ]
    },
    {
      "term": "프랑스인",
      "total": 2,
      "sourceCount": 1,
      "sources": [
        "yna"
      ],
      "examples": [
        {
          "source": "yna",
          "title": "한타바이러스 크루즈선 탑승 프랑스인 1명 확진(종합)"
        },
        {
          "source": "yna",
          "title": "\"프랑스인 10명 중 9명, 의료용 대마 합법화 찬성\""
        }
      ]
    },
    {
      "term": "방러",
      "total": 2,
      "sourceCount": 1,
      "sources": [
        "yna"
      ],
      "examples": [
        {
          "source": "yna",
          "title": "러 \"트럼프 방러 초청 여전히 유효, 푸틴이 환영할 것\"(종합)"
        },
        {
          "source": "yna",
          "title": "러 \"트럼프 방러 초청 여전히 유효, 푸틴이 환영할 것\""
        }
      ]
    },
    {
      "term": "초청",
      "total": 2,
      "sourceCount": 1,
      "sources": [
        "yna"
      ],
      "examples": [
        {
          "source": "yna",
          "title": "러 \"트럼프 방러 초청 여전히 유효, 푸틴이 환영할 것\"(종합)"
        },
        {
          "source": "yna",
          "title": "러 \"트럼프 방러 초청 여전히 유효, 푸틴이 환영할 것\""
        }
      ]
    },
    {
      "term": "여전히",
      "total": 2,
      "sourceCount": 1,
      "sources": [
        "yna"
      ],
      "examples": [
        {
          "source": "yna",
          "title": "러 \"트럼프 방러 초청 여전히 유효, 푸틴이 환영할 것\"(종합)"
        },
        {
          "source": "yna",
          "title": "러 \"트럼프 방러 초청 여전히 유효, 푸틴이 환영할 것\""
        }
      ]
    },
    {
      "term": "유효",
      "total": 2,
      "sourceCount": 1,
      "sources": [
        "yna"
      ],
      "examples": [
        {
          "source": "yna",
          "title": "러 \"트럼프 방러 초청 여전히 유효, 푸틴이 환영할 것\"(종합)"
        },
        {
          "source": "yna",
          "title": "러 \"트럼프 방러 초청 여전히 유효, 푸틴이 환영할 것\""
        }
      ]
    },
    {
      "term": "푸틴이",
      "total": 2,
      "sourceCount": 1,
      "sources": [
        "yna"
      ],
      "examples": [
        {
          "source": "yna",
          "title": "러 \"트럼프 방러 초청 여전히 유효, 푸틴이 환영할 것\"(종합)"
        },
        {
          "source": "yna",
          "title": "러 \"트럼프 방러 초청 여전히 유효, 푸틴이 환영할 것\""
        }
      ]
    },
    {
      "term": "환영할",
      "total": 2,
      "sourceCount": 1,
      "sources": [
        "yna"
      ],
      "examples": [
        {
          "source": "yna",
          "title": "러 \"트럼프 방러 초청 여전히 유효, 푸틴이 환영할 것\"(종합)"
        },
        {
          "source": "yna",
          "title": "러 \"트럼프 방러 초청 여전히 유효, 푸틴이 환영할 것\""
        }
      ]
    },
    {
      "term": "참패",
      "total": 2,
      "sourceCount": 1,
      "sources": [
        "yna"
      ],
      "examples": [
        {
          "source": "yna",
          "title": "지방선거 참패 후폭풍…노동당 내 반란 직면한 스타머"
        },
        {
          "source": "yna",
          "title": "'지방선거 참패' 스타머, 사임 압박 거부…영국 국채금리 상승"
        }
      ]
    },
    {
      "term": "가장",
      "total": 2,
      "sourceCount": 1,
      "sources": [
        "yna"
      ],
      "examples": [
        {
          "source": "yna",
          "title": "트럼프 \"휴전 유지되고 있지만 가장 약한 상태…연명장치 의존\""
        },
        {
          "source": "yna",
          "title": "[속보] 트럼프 \"이란전 휴전 가장 약한 상태…연명장치 의존\""
        }
      ]
    },
    {
      "term": "약한",
      "total": 2,
      "sourceCount": 1,
      "sources": [
        "yna"
      ],
      "examples": [
        {
          "source": "yna",
          "title": "트럼프 \"휴전 유지되고 있지만 가장 약한 상태…연명장치 의존\""
        },
        {
          "source": "yna",
          "title": "[속보] 트럼프 \"이란전 휴전 가장 약한 상태…연명장치 의존\""
        }
      ]
    },
    {
      "term": "상태",
      "total": 2,
      "sourceCount": 1,
      "sources": [
        "yna"
      ],
      "examples": [
        {
          "source": "yna",
          "title": "트럼프 \"휴전 유지되고 있지만 가장 약한 상태…연명장치 의존\""
        },
        {
          "source": "yna",
          "title": "[속보] 트럼프 \"이란전 휴전 가장 약한 상태…연명장치 의존\""
        }
      ]
    },
    {
      "term": "연명장치",
      "total": 2,
      "sourceCount": 1,
      "sources": [
        "yna"
      ],
      "examples": [
        {
          "source": "yna",
          "title": "트럼프 \"휴전 유지되고 있지만 가장 약한 상태…연명장치 의존\""
        },
        {
          "source": "yna",
          "title": "[속보] 트럼프 \"이란전 휴전 가장 약한 상태…연명장치 의존\""
        }
      ]
    },
    {
      "term": "이란전",
      "total": 2,
      "sourceCount": 1,
      "sources": [
        "yna"
      ],
      "examples": [
        {
          "source": "yna",
          "title": "[속보] 트럼프 \"이란전 휴전 가장 약한 상태…연명장치 의존\""
        },
        {
          "source": "yna",
          "title": "[속보] 美국방, 이란전 거론하며 \"파트너들이 어깨 나란히 해주길\""
        }
      ]
    },
    {
      "term": "판매",
      "total": 2,
      "sourceCount": 1,
      "sources": [
        "yna"
      ],
      "examples": [
        {
          "source": "yna",
          "title": "미 4월 기존주택 판매 0.2%↑…봄 성수기에도 부진"
        },
        {
          "source": "yna",
          "title": "여성 행세하며 '명품 헐값 판매' 사기…20억원 가로챈 남성 입건"
        }
      ]
    },
    {
      "term": "최선",
      "total": 2,
      "sourceCount": 1,
      "sources": [
        "yna"
      ],
      "examples": [
        {
          "source": "yna",
          "title": "안규백 \"韓주도 한반도 방위 최선\"…헤그세스 \"美에 협력하길\"(종합)"
        },
        {
          "source": "yna",
          "title": "[속보] 안규백 국방 \"한국주도의 한반도 방위 실현에 최선\""
        }
      ]
    },
    {
      "term": "인수",
      "total": 2,
      "sourceCount": 1,
      "sources": [
        "yna"
      ],
      "examples": [
        {
          "source": "yna",
          "title": "소니, 블랙스톤서 6조원에 음원저작권 인수…\"검증된 투자자산\""
        },
        {
          "source": "yna",
          "title": "日언론 \"MBK파트너스, 日알루미늄 업체 아르테미라 인수\""
        }
      ]
    },
    {
      "term": "연합뉴스",
      "total": 2,
      "sourceCount": 1,
      "sources": [
        "yna"
      ],
      "examples": [
        {
          "source": "yna",
          "title": "[알림] 연합뉴스 콘텐츠 저작권 고지"
        },
        {
          "source": "yna",
          "title": "[연합뉴스 이 시각 헤드라인] - 18:00"
        }
      ]
    },
    {
      "term": "정착민",
      "total": 2,
      "sourceCount": 1,
      "sources": [
        "yna"
      ],
      "examples": [
        {
          "source": "yna",
          "title": "EU, '요르단강 서안 폭력' 이스라엘 정착민 제재 합의(종합)"
        },
        {
          "source": "yna",
          "title": "EU, '서안지구 폭력' 이스라엘 정착민 제재 합의"
        }
      ]
    },
    {
      "term": "덮친",
      "total": 2,
      "sourceCount": 1,
      "sources": [
        "yna"
      ],
      "examples": [
        {
          "source": "yna",
          "title": "크루즈선 덮친 한타바이러스 확진 총 7명으로 늘어"
        },
        {
          "source": "yna",
          "title": "[영상] 한국 상선 덮친 '미상의 비행체'…정부의 대응 카드는"
        }
      ]
    },
    {
      "term": "최종",
      "total": 2,
      "sourceCount": 1,
      "sources": [
        "yna"
      ],
      "examples": [
        {
          "source": "yna",
          "title": "삼성전자 노사 사후조정 첫날 결론없이 종료…내일 최종 판가름(종합)"
        },
        {
          "source": "yna",
          "title": "필리핀 두테르테 부통령 또 탄핵안 가결…상원이 최종 심판"
        }
      ]
    },
    {
      "term": "연어",
      "total": 2,
      "sourceCount": 1,
      "sources": [
        "yna"
      ],
      "examples": [
        {
          "source": "yna",
          "title": "'연어 술파티' 박상용 대검서 6시간 징계심의…朴 \"충실히 소명\"(종합2보)"
        },
        {
          "source": "yna",
          "title": "대검 감찰위, '연어 술파티' 박상용 징계심의…朴 \"충실히 소명\"(종합)"
        }
      ]
    },
    {
      "term": "술파티",
      "total": 2,
      "sourceCount": 1,
      "sources": [
        "yna"
      ],
      "examples": [
        {
          "source": "yna",
          "title": "'연어 술파티' 박상용 대검서 6시간 징계심의…朴 \"충실히 소명\"(종합2보)"
        },
        {
          "source": "yna",
          "title": "대검 감찰위, '연어 술파티' 박상용 징계심의…朴 \"충실히 소명\"(종합)"
        }
      ]
    },
    {
      "term": "징계심의",
      "total": 2,
      "sourceCount": 1,
      "sources": [
        "yna"
      ],
      "examples": [
        {
          "source": "yna",
          "title": "'연어 술파티' 박상용 대검서 6시간 징계심의…朴 \"충실히 소명\"(종합2보)"
        },
        {
          "source": "yna",
          "title": "대검 감찰위, '연어 술파티' 박상용 징계심의…朴 \"충실히 소명\"(종합)"
        }
      ]
    },
    {
      "term": "충실히",
      "total": 2,
      "sourceCount": 1,
      "sources": [
        "yna"
      ],
      "examples": [
        {
          "source": "yna",
          "title": "'연어 술파티' 박상용 대검서 6시간 징계심의…朴 \"충실히 소명\"(종합2보)"
        },
        {
          "source": "yna",
          "title": "대검 감찰위, '연어 술파티' 박상용 징계심의…朴 \"충실히 소명\"(종합)"
        }
      ]
    },
    {
      "term": "공사장서",
      "total": 2,
      "sourceCount": 1,
      "sources": [
        "yna"
      ],
      "examples": [
        {
          "source": "yna",
          "title": "대전 공사장서 외국인 노동자 향해 둔기 휘두른 50대 입건"
        },
        {
          "source": "yna",
          "title": "정선 송전철탑 공사장서 50대 작업자 12ｍ 아래로 추락해 숨져(종합)"
        }
      ]
    },
    {
      "term": "대검",
      "total": 2,
      "sourceCount": 1,
      "sources": [
        "yna"
      ],
      "examples": [
        {
          "source": "yna",
          "title": "특검, '심우정 내란가담' 대검 압수수색…헌법존중TF 자료 확보(종합)"
        },
        {
          "source": "yna",
          "title": "대검 감찰위, '연어 술파티' 박상용 징계심의…朴 \"충실히 소명\"(종합)"
        }
      ]
    },
    {
      "term": "주민",
      "total": 2,
      "sourceCount": 1,
      "sources": [
        "yna"
      ],
      "examples": [
        {
          "source": "yna",
          "title": "김제 주택에서 불…80대 주민 연기흡입 이송"
        },
        {
          "source": "yna",
          "title": "층간소음 불만에 위층 주민 흉기로 살해한 20대 구속"
        }
      ]
    },
    {
      "term": "사임",
      "total": 2,
      "sourceCount": 1,
      "sources": [
        "yna"
      ],
      "examples": [
        {
          "source": "yna",
          "title": "라트비아 국방장관 날린 우크라 드론…영공침범에 사임"
        },
        {
          "source": "yna",
          "title": "'지방선거 참패' 스타머, 사임 압박 거부…영국 국채금리 상승"
        }
      ]
    },
    {
      "term": "옹진에",
      "total": 2,
      "sourceCount": 1,
      "sources": [
        "yna"
      ],
      "examples": [
        {
          "source": "yna",
          "title": "인천 옹진에 호우주의보 해제"
        },
        {
          "source": "yna",
          "title": "인천 옹진에 호우주의보"
        }
      ]
    },
    {
      "term": "호우주의보",
      "total": 2,
      "sourceCount": 1,
      "sources": [
        "yna"
      ],
      "examples": [
        {
          "source": "yna",
          "title": "인천 옹진에 호우주의보 해제"
        },
        {
          "source": "yna",
          "title": "인천 옹진에 호우주의보"
        }
      ]
    },
    {
      "term": "직원",
      "total": 2,
      "sourceCount": 1,
      "sources": [
        "yna"
      ],
      "examples": [
        {
          "source": "yna",
          "title": "검찰, 백해룡 '세관 직원 명예훼손' 의혹 수사 착수"
        },
        {
          "source": "yna",
          "title": "국조실 직원, 식당 업무방해 혐의 받아…\"직위해제 등 엄정조치\""
        }
      ]
    }
  ]
}