{
  "fetchedAt": "2026-06-30T17:21:52.586Z",
  "elapsedMs": 1909,
  "sourceTotal": 7,
  "sourceSuccess": 6,
  "sourceFail": 1,
  "totalHeadlines": 330,
  "uniqueKeywords": 243,
  "multiSourceCount": 100,
  "sources": [
    {
      "id": "sbs",
      "name": "SBS",
      "url": "https://news.sbs.co.kr/news/SectionRssFeed.do?sectionId=01",
      "status": "fail",
      "itemCount": 0,
      "elapsedMs": 547
    },
    {
      "id": "yna",
      "name": "연합뉴스",
      "url": "https://www.yna.co.kr/rss/news.xml",
      "status": "ok",
      "itemCount": 120,
      "elapsedMs": 890
    },
    {
      "id": "donga",
      "name": "동아일보",
      "url": "https://rss.donga.com/total.xml",
      "status": "ok",
      "itemCount": 50,
      "elapsedMs": 1497
    },
    {
      "id": "khan",
      "name": "경향신문",
      "url": "https://www.khan.co.kr/rss/rssdata/total_news.xml",
      "status": "ok",
      "itemCount": 50,
      "elapsedMs": 1073
    },
    {
      "id": "mk",
      "name": "매일경제",
      "url": "https://www.mk.co.kr/rss/30000001/",
      "status": "ok",
      "itemCount": 50,
      "elapsedMs": 906
    },
    {
      "id": "kmib",
      "name": "국민일보",
      "url": "https://www.kmib.co.kr/rss/data/kmibRssAll.xml",
      "status": "ok",
      "itemCount": 30,
      "elapsedMs": 1219
    },
    {
      "id": "hani",
      "name": "한겨레",
      "url": "https://www.hani.co.kr/rss",
      "status": "ok",
      "itemCount": 30,
      "elapsedMs": 1841
    }
  ],
  "multiSourceKeywords": [
    {
      "term": "총리",
      "total": 13,
      "sourceCount": 5,
      "sources": [
        "yna",
        "donga",
        "khan",
        "mk",
        "hani"
      ],
      "examples": [
        {
          "source": "yna",
          "title": "[월드컵] 독일 총리 \"대단한 경기\" 위로했다가 뭇매(종합)"
        },
        {
          "source": "yna",
          "title": "마지막 날 경찰·소방 찾은 金총리…\"후임 총리도 챙겨주시길\""
        },
        {
          "source": "yna",
          "title": "李대통령, 한성숙 총리 임명안 재가…역대 두번째 여성총리 탄생"
        }
      ]
    },
    {
      "term": "한성숙",
      "total": 10,
      "sourceCount": 5,
      "sources": [
        "yna",
        "donga",
        "khan",
        "mk",
        "hani"
      ],
      "examples": [
        {
          "source": "yna",
          "title": "李대통령, 한성숙 총리 임명안 재가…역대 두번째 여성총리 탄생"
        },
        {
          "source": "yna",
          "title": "한성숙 총리 후보 임명동의안 與주도 국회 통과…국힘 보이콧(종합)"
        },
        {
          "source": "yna",
          "title": "한성숙 총리 후보자 임명동의안 與주도 국회 통과…국힘 불참"
        }
      ]
    },
    {
      "term": "인사",
      "total": 10,
      "sourceCount": 4,
      "sources": [
        "yna",
        "donga",
        "khan",
        "mk"
      ],
      "examples": [
        {
          "source": "yna",
          "title": "[인사] 강원특별자치도소방본부"
        },
        {
          "source": "yna",
          "title": "[인사] 강원대학교"
        },
        {
          "source": "yna",
          "title": "유리천장 깨는 교황의 인사…이탈리아 수녀, 교황청 장관 됐다"
        }
      ]
    },
    {
      "term": "반도체",
      "total": 9,
      "sourceCount": 4,
      "sources": [
        "yna",
        "khan",
        "mk",
        "hani"
      ],
      "examples": [
        {
          "source": "yna",
          "title": "전남광주특별시의회, '반도체 지원 조례' 1호 안건 의결"
        },
        {
          "source": "khan",
          "title": "전남광주통합시의회 1호 조례는 ‘반도체 투자 지원’"
        },
        {
          "source": "khan",
          "title": "‘탈 경부축’ 반도체 생태계…전향적 시도, 균형발전 체감은 숙제"
        }
      ]
    },
    {
      "term": "트럼프",
      "total": 8,
      "sourceCount": 4,
      "sources": [
        "yna",
        "donga",
        "khan",
        "hani"
      ],
      "examples": [
        {
          "source": "yna",
          "title": "트럼프 \"출생시민권 유지, 큰 불행…의회입법으로 만회 가능\""
        },
        {
          "source": "yna",
          "title": "美 '출생시민권' 유지된다…대법원, 트럼프 이민정책에 제동(종합)"
        },
        {
          "source": "yna",
          "title": "美대법, '출생시민권' 유지 판결…트럼프 이민정책에 제동"
        }
      ]
    },
    {
      "term": "대통령",
      "total": 7,
      "sourceCount": 4,
      "sources": [
        "yna",
        "khan",
        "mk",
        "hani"
      ],
      "examples": [
        {
          "source": "yna",
          "title": "李대통령, 한성숙 총리 임명안 재가…역대 두번째 여성총리 탄생"
        },
        {
          "source": "yna",
          "title": "李대통령, '서남권 국민보고회' 참석…산단 후보지 항공시찰도(종합2보)"
        },
        {
          "source": "khan",
          "title": "이 대통령 “제가 용인·서남권 투자 동시 진행 제안”"
        }
      ]
    },
    {
      "term": "서남권",
      "total": 5,
      "sourceCount": 4,
      "sources": [
        "yna",
        "khan",
        "mk",
        "hani"
      ],
      "examples": [
        {
          "source": "yna",
          "title": "李대통령, '서남권 국민보고회' 참석…산단 후보지 항공시찰도(종합2보)"
        },
        {
          "source": "khan",
          "title": "이 대통령 “제가 용인·서남권 투자 동시 진행 제안”"
        },
        {
          "source": "mk",
          "title": "[포토] 헬기서 서남권 시찰하는 李대통령"
        }
      ]
    },
    {
      "term": "국내",
      "total": 4,
      "sourceCount": 4,
      "sources": [
        "yna",
        "donga",
        "khan",
        "mk"
      ],
      "examples": [
        {
          "source": "yna",
          "title": "아르헨 밀레이, 메르코수르 정상회의 불참…국내 정치일정 택해"
        },
        {
          "source": "donga",
          "title": "테슬라 “구형 모델도 최신 완전자율주행”… 국내 업계 긴장"
        },
        {
          "source": "khan",
          "title": "국내 상장사 27%, 이자도 못 갚는다"
        }
      ]
    },
    {
      "term": "만에",
      "total": 4,
      "sourceCount": 4,
      "sources": [
        "yna",
        "donga",
        "khan",
        "mk"
      ],
      "examples": [
        {
          "source": "yna",
          "title": "미 5월 구인규모 예상밖 호조 지속…2년 만에 최대"
        },
        {
          "source": "donga",
          "title": "‘흥행 열풍’ 프로야구, 역대 최소 388경기 만에 700만 관중 달성"
        },
        {
          "source": "khan",
          "title": "공공차량 2부제 해제…원유 수급 숨통, 석 달 만에 정상화"
        }
      ]
    },
    {
      "term": "공급",
      "total": 4,
      "sourceCount": 4,
      "sources": [
        "donga",
        "khan",
        "mk",
        "hani"
      ],
      "examples": [
        {
          "source": "donga",
          "title": "삼성전기, 빅테크에 4500억 규모 MLCC 공급"
        },
        {
          "source": "khan",
          "title": "오세훈 “대학생 특화 원룸 1만실 공급”"
        },
        {
          "source": "mk",
          "title": "삼성전기 불기둥 이유 있었네…글로벌빅테크에 4500억 MLCC 공급"
        }
      ]
    },
    {
      "term": "국힘",
      "total": 12,
      "sourceCount": 3,
      "sources": [
        "yna",
        "mk",
        "hani"
      ],
      "examples": [
        {
          "source": "yna",
          "title": "한성숙 총리 후보 임명동의안 與주도 국회 통과…국힘 보이콧(종합)"
        },
        {
          "source": "yna",
          "title": "한성숙 총리 후보자 임명동의안 與주도 국회 통과…국힘 불참"
        },
        {
          "source": "yna",
          "title": "법사 포함 10개 상임위·예결위원장 與주도 선출…국힘 표결 불참(종합)"
        }
      ]
    },
    {
      "term": "국회",
      "total": 8,
      "sourceCount": 3,
      "sources": [
        "yna",
        "khan",
        "mk"
      ],
      "examples": [
        {
          "source": "yna",
          "title": "한성숙 총리 후보 임명동의안 與주도 국회 통과…국힘 보이콧(종합)"
        },
        {
          "source": "yna",
          "title": "한성숙 총리 후보자 임명동의안 與주도 국회 통과…국힘 불참"
        },
        {
          "source": "yna",
          "title": "[속보] 한성숙 총리 후보 인준안 국회 통과…국힘은 표결 보이콧"
        }
      ]
    },
    {
      "term": "통과",
      "total": 8,
      "sourceCount": 3,
      "sources": [
        "yna",
        "khan",
        "mk"
      ],
      "examples": [
        {
          "source": "yna",
          "title": "한성숙 총리 후보 임명동의안 與주도 국회 통과…국힘 보이콧(종합)"
        },
        {
          "source": "yna",
          "title": "작년 준우승자 아니시모바, 윔블던테니스 1회전 가볍게 통과"
        },
        {
          "source": "yna",
          "title": "한성숙 총리 후보자 임명동의안 與주도 국회 통과…국힘 불참"
        }
      ]
    },
    {
      "term": "후보",
      "total": 6,
      "sourceCount": 3,
      "sources": [
        "yna",
        "mk",
        "hani"
      ],
      "examples": [
        {
          "source": "yna",
          "title": "한성숙 총리 후보 임명동의안 與주도 국회 통과…국힘 보이콧(종합)"
        },
        {
          "source": "yna",
          "title": "[속보] 한성숙 총리 후보 인준안 국회 통과…국힘은 표결 보이콧"
        },
        {
          "source": "mk",
          "title": "[속보] 한성숙 총리 후보 인준안 국회 통과…국힘은 표결 보이콧"
        }
      ]
    },
    {
      "term": "투자",
      "total": 6,
      "sourceCount": 3,
      "sources": [
        "khan",
        "mk",
        "hani"
      ],
      "examples": [
        {
          "source": "khan",
          "title": "전남광주통합시의회 1호 조례는 ‘반도체 투자 지원’"
        },
        {
          "source": "khan",
          "title": "이 대통령 “제가 용인·서남권 투자 동시 진행 제안”"
        },
        {
          "source": "khan",
          "title": "“투자 환영” 시민대회에 노사 협력 선언…광주전남 ‘들썩’"
        }
      ]
    },
    {
      "term": "제동",
      "total": 5,
      "sourceCount": 3,
      "sources": [
        "yna",
        "donga",
        "hani"
      ],
      "examples": [
        {
          "source": "yna",
          "title": "美 '출생시민권' 유지된다…대법원, 트럼프 이민정책에 제동(종합)"
        },
        {
          "source": "yna",
          "title": "美대법, '출생시민권' 유지 판결…트럼프 이민정책에 제동"
        },
        {
          "source": "yna",
          "title": "[속보] 美대법원, '출생시민권 금지' 트럼프 이민정책에 제동"
        }
      ]
    },
    {
      "term": "출범",
      "total": 5,
      "sourceCount": 3,
      "sources": [
        "yna",
        "donga",
        "mk"
      ],
      "examples": [
        {
          "source": "yna",
          "title": "전남광주통합교육청 출범…초광역 교육청 시대 개막"
        },
        {
          "source": "yna",
          "title": "대한민국 1호 광역행정통합 '전남광주특별시' 출범"
        },
        {
          "source": "donga",
          "title": "NH투자증권 새 경영체제 출범… 신재욱-배광수 각자 대표 선임"
        }
      ]
    },
    {
      "term": "임명동의안",
      "total": 5,
      "sourceCount": 3,
      "sources": [
        "yna",
        "khan",
        "hani"
      ],
      "examples": [
        {
          "source": "yna",
          "title": "한성숙 총리 후보 임명동의안 與주도 국회 통과…국힘 보이콧(종합)"
        },
        {
          "source": "yna",
          "title": "한성숙 총리 후보자 임명동의안 與주도 국회 통과…국힘 불참"
        },
        {
          "source": "khan",
          "title": "한성숙 총리 임명동의안, 여당 주도로 통과"
        }
      ]
    },
    {
      "term": "상임위",
      "total": 5,
      "sourceCount": 3,
      "sources": [
        "yna",
        "khan",
        "mk"
      ],
      "examples": [
        {
          "source": "yna",
          "title": "법사 포함 10개 상임위·예결위원장 與주도 선출…국힘 표결 불참(종합)"
        },
        {
          "source": "yna",
          "title": "법사 포함 10개 상임위·예결위원장 與주도 선출…국힘 반발"
        },
        {
          "source": "yna",
          "title": "국힘 \"趙의장 강제배정 11개 상임위, 국힘 위원 전원 사임\""
        }
      ]
    },
    {
      "term": "예결위원장",
      "total": 5,
      "sourceCount": 3,
      "sources": [
        "yna",
        "khan",
        "hani"
      ],
      "examples": [
        {
          "source": "yna",
          "title": "법사 포함 10개 상임위·예결위원장 與주도 선출…국힘 표결 불참(종합)"
        },
        {
          "source": "yna",
          "title": "[프로필] 이광재 예결위원장…실용노선 걷는 노무현의 오른팔"
        },
        {
          "source": "yna",
          "title": "법사 포함 10개 상임위·예결위원장 與주도 선출…국힘 반발"
        }
      ]
    },
    {
      "term": "대법원",
      "total": 4,
      "sourceCount": 3,
      "sources": [
        "yna",
        "khan",
        "hani"
      ],
      "examples": [
        {
          "source": "yna",
          "title": "美 '출생시민권' 유지된다…대법원, 트럼프 이민정책에 제동(종합)"
        },
        {
          "source": "yna",
          "title": "[속보] 美대법원, '출생시민권 금지' 트럼프 이민정책에 제동"
        },
        {
          "source": "khan",
          "title": "“독립 규제기관 위원 해임도 대통령 권한” 트럼프 ‘인사 보복’ 힘 실어준 미 대법원"
        }
      ]
    },
    {
      "term": "이란",
      "total": 4,
      "sourceCount": 3,
      "sources": [
        "yna",
        "khan",
        "hani"
      ],
      "examples": [
        {
          "source": "yna",
          "title": "이란 외무부 \"향후 며칠간 'MOU 이행' 평가 후 최종 회담 결정\""
        },
        {
          "source": "khan",
          "title": "‘순교자 하메네이’…이란, 장례식 앞두고 ‘내부 결속 다지기’"
        },
        {
          "source": "hani",
          "title": "호르무즈 충돌 뒤, 미-이란 카타르 모인다…얼굴 맞대진 않아"
        }
      ]
    },
    {
      "term": "경찰",
      "total": 4,
      "sourceCount": 3,
      "sources": [
        "yna",
        "donga",
        "khan"
      ],
      "examples": [
        {
          "source": "yna",
          "title": "마지막 날 경찰·소방 찾은 金총리…\"후임 총리도 챙겨주시길\""
        },
        {
          "source": "donga",
          "title": "SUV 바퀴에 다리 깔린 8세 여아, 경찰·시민 힘 합쳐 구조"
        },
        {
          "source": "donga",
          "title": "金총리, 퇴임 앞 ‘올공 시위’ 대응 경찰 격려…“헌신 잊지 않겠다”"
        }
      ]
    },
    {
      "term": "역대",
      "total": 4,
      "sourceCount": 3,
      "sources": [
        "yna",
        "donga",
        "mk"
      ],
      "examples": [
        {
          "source": "yna",
          "title": "李대통령, 한성숙 총리 임명안 재가…역대 두번째 여성총리 탄생"
        },
        {
          "source": "yna",
          "title": "북중미 월드컵에도 뜨거운 프로야구…역대 최소 경기 700만 관중"
        },
        {
          "source": "donga",
          "title": "‘흥행 열풍’ 프로야구, 역대 최소 388경기 만에 700만 관중 달성"
        }
      ]
    },
    {
      "term": "있어",
      "total": 4,
      "sourceCount": 3,
      "sources": [
        "yna",
        "donga",
        "mk"
      ],
      "examples": [
        {
          "source": "yna",
          "title": "키움 안우진, LG전 5⅔이닝 11K 역투 \"예전 모습 찾아가고 있어\"(종합)"
        },
        {
          "source": "donga",
          "title": "‘억대 도박빚’ 고백한 예비 신랑…예비 신부 “정이 있어 가보려 한다”"
        },
        {
          "source": "donga",
          "title": "던 “5년 안에 은퇴 고민…빨리 잊히고 싶은 마음 있어”"
        }
      ]
    },
    {
      "term": "서영교",
      "total": 4,
      "sourceCount": 3,
      "sources": [
        "yna",
        "khan",
        "mk"
      ],
      "examples": [
        {
          "source": "yna",
          "title": "[프로필] 서영교 법사위원장…'태완이법·구하라법' 주도 4선 중진"
        },
        {
          "source": "khan",
          "title": "국회 후반기 법사위원장에 서영교…10개 상임위·예결위원장 민주당으로"
        },
        {
          "source": "khan",
          "title": "후반기 법사위원장에 서영교…정무위·재경위도 민주당에"
        }
      ]
    },
    {
      "term": "경제",
      "total": 4,
      "sourceCount": 3,
      "sources": [
        "yna",
        "donga",
        "mk"
      ],
      "examples": [
        {
          "source": "yna",
          "title": "민주콩고 에볼라 사망자 보름새 2배…\"5조원대 경제 손실 우려\""
        },
        {
          "source": "donga",
          "title": "[지표로 보는 경제]7월 1일"
        },
        {
          "source": "mk",
          "title": "경제6단체, 합리적 온실가스 감축경로 마련 촉구 건의서 전달"
        }
      ]
    },
    {
      "term": "상장사",
      "total": 4,
      "sourceCount": 3,
      "sources": [
        "donga",
        "khan",
        "mk"
      ],
      "examples": [
        {
          "source": "donga",
          "title": "상장사 4곳중 1곳은 한계기업… 주요 국가중 가장 빠르게 늘었다"
        },
        {
          "source": "khan",
          "title": "국내 상장사 27%, 이자도 못 갚는다"
        },
        {
          "source": "khan",
          "title": "“혁신 시장”이 무색…코스닥 상장사 4곳 중 1곳, 연구·개발비 ‘0’"
        }
      ]
    },
    {
      "term": "가능",
      "total": 3,
      "sourceCount": 3,
      "sources": [
        "yna",
        "donga",
        "khan"
      ],
      "examples": [
        {
          "source": "yna",
          "title": "트럼프 \"출생시민권 유지, 큰 불행…의회입법으로 만회 가능\""
        },
        {
          "source": "donga",
          "title": "체불임금 6개월까지 국가가 지급… 1주일 육아휴직도 가능"
        },
        {
          "source": "khan",
          "title": "1주일 육아휴직도 가능…외환시장 ‘24시간 거래’ 시대 열린다[하반기 달라지는 것들]"
        }
      ]
    },
    {
      "term": "시대",
      "total": 3,
      "sourceCount": 3,
      "sources": [
        "yna",
        "donga",
        "khan"
      ],
      "examples": [
        {
          "source": "yna",
          "title": "전남광주통합교육청 출범…초광역 교육청 시대 개막"
        },
        {
          "source": "donga",
          "title": "AI 수출통제 시대, 한국의 디지털 전략 자산은?[기고/박성호]"
        },
        {
          "source": "khan",
          "title": "1주일 육아휴직도 가능…외환시장 ‘24시간 거래’ 시대 열린다[하반기 달라지는 것들]"
        }
      ]
    },
    {
      "term": "우크라",
      "total": 3,
      "sourceCount": 3,
      "sources": [
        "yna",
        "donga",
        "khan"
      ],
      "examples": [
        {
          "source": "yna",
          "title": "모나코 주택가 폭탄 테러…우크라 '친러 재벌' 부부 중상(종합2보)"
        },
        {
          "source": "donga",
          "title": "“모스크바 외곽 러 우주통신센터, 8일만에 또 우크라 드론 피격”"
        },
        {
          "source": "khan",
          "title": "한·우크라 “포로 송환, 북한군 자유의사 존중…국제법 따를 것”"
        }
      ]
    },
    {
      "term": "삼성",
      "total": 3,
      "sourceCount": 3,
      "sources": [
        "yna",
        "khan",
        "mk"
      ],
      "examples": [
        {
          "source": "yna",
          "title": "[프로야구 창원전적] 삼성 13-7 NC"
        },
        {
          "source": "khan",
          "title": "AI 활용 역량 극대화…삼성 청년 아카데미"
        },
        {
          "source": "mk",
          "title": "李 \"용인·서남권 동시추진 제안에 삼성·SK도 동의\""
        }
      ]
    },
    {
      "term": "차량",
      "total": 3,
      "sourceCount": 3,
      "sources": [
        "yna",
        "donga",
        "khan"
      ],
      "examples": [
        {
          "source": "yna",
          "title": "1t 화물차, 앞서가던 차량 2대 추돌…60대 운전자 숨져"
        },
        {
          "source": "donga",
          "title": "“정비 차량 들어오기전부터 원격으로 상태 점검”"
        },
        {
          "source": "khan",
          "title": "차 바퀴에 다리 낀 8세 아이···경찰 요청에 시민 10여명 차량 들었다"
        }
      ]
    },
    {
      "term": "통보",
      "total": 3,
      "sourceCount": 3,
      "sources": [
        "yna",
        "khan",
        "mk"
      ],
      "examples": [
        {
          "source": "yna",
          "title": "野\"위철환, 진상위 조사내용 미리알아\"…선관위 \"발표직전 통보\"(종합)"
        },
        {
          "source": "khan",
          "title": "“김건희, 이원모 통해 조사 하루 전 검찰에 ‘날짜 통보’”···검찰은 ‘예상 답변서’ 준비 정황"
        },
        {
          "source": "mk",
          "title": "‘음료 3잔’ 횡령했다고 알바생 고소한 사장...결국 빽다방은 영업종료 통보"
        }
      ]
    },
    {
      "term": "법사위",
      "total": 3,
      "sourceCount": 3,
      "sources": [
        "yna",
        "mk",
        "hani"
      ],
      "examples": [
        {
          "source": "yna",
          "title": "국힘 \"與, 무슨 염치로 법사위 가져가나…공소취소 통과 목적\""
        },
        {
          "source": "mk",
          "title": "[속보] 與, 상임위 11곳 위원장 후보 추천…법사위 서영교"
        },
        {
          "source": "hani",
          "title": "[사설] 결국 여 단독 원 구성, 이런 일 또 없게 법사위 근본 손질을"
        }
      ]
    },
    {
      "term": "날씨",
      "total": 3,
      "sourceCount": 3,
      "sources": [
        "yna",
        "donga",
        "khan"
      ],
      "examples": [
        {
          "source": "yna",
          "title": "[날씨] 내일 남부·제주 강한 비…수도권·강원은 소나기"
        },
        {
          "source": "donga",
          "title": "[날씨]낮 최고 33도 ‘찜통더위’…오후 수도권·강원 소나기"
        },
        {
          "source": "khan",
          "title": "[2026년 07월 01일 날씨]제주에 ‘지각 장마’…남쪽은 물폭탄, 내륙은 찜통"
        }
      ]
    },
    {
      "term": "수도권",
      "total": 3,
      "sourceCount": 3,
      "sources": [
        "yna",
        "donga",
        "hani"
      ],
      "examples": [
        {
          "source": "yna",
          "title": "[날씨] 내일 남부·제주 강한 비…수도권·강원은 소나기"
        },
        {
          "source": "donga",
          "title": "[날씨]낮 최고 33도 ‘찜통더위’…오후 수도권·강원 소나기"
        },
        {
          "source": "hani",
          "title": "반도체 품고 하나 된 전남·광주…수도권 견줄 ‘300조 경제권’ 목표"
        }
      ]
    },
    {
      "term": "협력",
      "total": 3,
      "sourceCount": 3,
      "sources": [
        "yna",
        "khan",
        "mk"
      ],
      "examples": [
        {
          "source": "yna",
          "title": "외교부, 적십자·적신월사연맹과 인도지원 협력 증진 논의"
        },
        {
          "source": "khan",
          "title": "“투자 환영” 시민대회에 노사 협력 선언…광주전남 ‘들썩’"
        },
        {
          "source": "mk",
          "title": "한국투자증권, 모간스탠리운용과 협력 추진"
        }
      ]
    },
    {
      "term": "이병희",
      "total": 3,
      "sourceCount": 3,
      "sources": [
        "yna",
        "mk",
        "hani"
      ],
      "examples": [
        {
          "source": "yna",
          "title": "한국노동연구원 원장에 이병희 선임연구위원…임기 3년"
        },
        {
          "source": "mk",
          "title": "노동연구원장 이병희, 국토연구원장 임재만, 통일연구원장 권만학"
        },
        {
          "source": "hani",
          "title": "노동연구원 새 원장에 이병희 선임연구위원"
        }
      ]
    },
    {
      "term": "경영권",
      "total": 3,
      "sourceCount": 3,
      "sources": [
        "khan",
        "mk",
        "hani"
      ],
      "examples": [
        {
          "source": "khan",
          "title": "중앙일보 “경영권 매각” 워크아웃 돌파구"
        },
        {
          "source": "mk",
          "title": "에코프로비엠 1.2조 유상증자 … 印尼 니켈제련소 경영권 확보"
        },
        {
          "source": "hani",
          "title": "“팔릴 매물은 중앙일보뿐…경영권 매각, 자구안에 담아”"
        }
      ]
    },
    {
      "term": "매각",
      "total": 3,
      "sourceCount": 3,
      "sources": [
        "khan",
        "mk",
        "hani"
      ],
      "examples": [
        {
          "source": "khan",
          "title": "중앙일보 “경영권 매각” 워크아웃 돌파구"
        },
        {
          "source": "mk",
          "title": "코오롱인더 반도체사업부 IMM에 매각"
        },
        {
          "source": "hani",
          "title": "“팔릴 매물은 중앙일보뿐…경영권 매각, 자구안에 담아”"
        }
      ]
    },
    {
      "term": "결국",
      "total": 3,
      "sourceCount": 3,
      "sources": [
        "khan",
        "mk",
        "hani"
      ],
      "examples": [
        {
          "source": "khan",
          "title": "‘청년 고용 눈치보기’ 정년 연장 숙제, 결국 하반기로 미뤘다"
        },
        {
          "source": "mk",
          "title": "‘음료 3잔’ 횡령했다고 알바생 고소한 사장...결국 빽다방은 영업종료 통보"
        },
        {
          "source": "hani",
          "title": "[사설] 결국 여 단독 원 구성, 이런 일 또 없게 법사위 근본 손질을"
        }
      ]
    },
    {
      "term": "프로필",
      "total": 12,
      "sourceCount": 2,
      "sources": [
        "yna",
        "donga"
      ],
      "examples": [
        {
          "source": "yna",
          "title": "[프로필] 서삼석 농해수위원장…지방 행정 아우른 '호남 풀뿌리'"
        },
        {
          "source": "yna",
          "title": "[프로필] 이재정 문체위원장…인권변호사 출신 3선"
        },
        {
          "source": "yna",
          "title": "[프로필] 조승래 재경위원장…수석대변인·사무총장 역임한 3선"
        }
      ]
    },
    {
      "term": "프로야구",
      "total": 9,
      "sourceCount": 2,
      "sources": [
        "yna",
        "donga"
      ],
      "examples": [
        {
          "source": "yna",
          "title": "[프로야구] 1일 선발투수"
        },
        {
          "source": "yna",
          "title": "[프로야구 중간순위] 30일"
        },
        {
          "source": "yna",
          "title": "[프로야구 창원전적] 삼성 13-7 NC"
        }
      ]
    },
    {
      "term": "월드컵",
      "total": 7,
      "sourceCount": 2,
      "sources": [
        "yna",
        "khan"
      ],
      "examples": [
        {
          "source": "yna",
          "title": "[월드컵] 독일 총리 \"대단한 경기\" 위로했다가 뭇매(종합)"
        },
        {
          "source": "yna",
          "title": "◇내일의 월드컵(2일)"
        },
        {
          "source": "yna",
          "title": "◇오늘의 월드컵(1일)"
        }
      ]
    },
    {
      "term": "키움",
      "total": 6,
      "sourceCount": 2,
      "sources": [
        "yna",
        "donga"
      ],
      "examples": [
        {
          "source": "yna",
          "title": "KIA 김도영 24·25홈런 '쾅쾅'…키움 안우진 5⅔이닝 11탈삼진(종합2보)"
        },
        {
          "source": "yna",
          "title": "키움 안우진, LG전 5⅔이닝 11K 역투 \"예전 모습 찾아가고 있어\"(종합)"
        },
        {
          "source": "yna",
          "title": "KIA 김도영 24·25홈런 '쾅쾅'…키움 안우진 5⅔이닝 11탈삼진(종합)"
        }
      ]
    },
    {
      "term": "주도",
      "total": 6,
      "sourceCount": 2,
      "sources": [
        "yna",
        "khan"
      ],
      "examples": [
        {
          "source": "yna",
          "title": "한성숙 총리 후보 임명동의안 與주도 국회 통과…국힘 보이콧(종합)"
        },
        {
          "source": "yna",
          "title": "한성숙 총리 후보자 임명동의안 與주도 국회 통과…국힘 불참"
        },
        {
          "source": "yna",
          "title": "법사 포함 10개 상임위·예결위원장 與주도 선출…국힘 표결 불참(종합)"
        }
      ]
    },
    {
      "term": "출생시민권",
      "total": 5,
      "sourceCount": 2,
      "sources": [
        "yna",
        "donga"
      ],
      "examples": [
        {
          "source": "yna",
          "title": "트럼프 \"출생시민권 유지, 큰 불행…의회입법으로 만회 가능\""
        },
        {
          "source": "yna",
          "title": "美 '출생시민권' 유지된다…대법원, 트럼프 이민정책에 제동(종합)"
        },
        {
          "source": "yna",
          "title": "美대법, '출생시민권' 유지 판결…트럼프 이민정책에 제동"
        }
      ]
    },
    {
      "term": "선출",
      "total": 5,
      "sourceCount": 2,
      "sources": [
        "yna",
        "hani"
      ],
      "examples": [
        {
          "source": "yna",
          "title": "초대 전남광주통합특별시의희 의장에 송형곤 의원 선출"
        },
        {
          "source": "yna",
          "title": "법사 포함 10개 상임위·예결위원장 與주도 선출…국힘 표결 불참(종합)"
        },
        {
          "source": "yna",
          "title": "법사 포함 10개 상임위·예결위원장 與주도 선출…국힘 반발"
        }
      ]
    },
    {
      "term": "홈런",
      "total": 5,
      "sourceCount": 2,
      "sources": [
        "yna",
        "donga"
      ],
      "examples": [
        {
          "source": "yna",
          "title": "KIA 김도영 24·25홈런 '쾅쾅'…키움 안우진 5⅔이닝 11탈삼진(종합2보)"
        },
        {
          "source": "yna",
          "title": "KIA 김도영 24·25홈런 '쾅쾅'…키움 안우진 5⅔이닝 11탈삼진(종합)"
        },
        {
          "source": "yna",
          "title": "폭우에 날아간 강백호 20호 홈런…한화 7-0에서 우천 노게임"
        }
      ]
    },
    {
      "term": "청년",
      "total": 5,
      "sourceCount": 2,
      "sources": [
        "khan",
        "hani"
      ],
      "examples": [
        {
          "source": "khan",
          "title": "김민석 “청년 등 남은 문제는 국회·당 돌아가서 해결”"
        },
        {
          "source": "khan",
          "title": "‘청년 고용 눈치보기’ 정년 연장 숙제, 결국 하반기로 미뤘다"
        },
        {
          "source": "khan",
          "title": "청년·신혼·노인 위한 1780가구 마련"
        }
      ]
    },
    {
      "term": "독일",
      "total": 4,
      "sourceCount": 2,
      "sources": [
        "yna",
        "donga"
      ],
      "examples": [
        {
          "source": "yna",
          "title": "[월드컵] 독일 총리 \"대단한 경기\" 위로했다가 뭇매(종합)"
        },
        {
          "source": "yna",
          "title": "[월드컵] 파라과이, 독일 꺾고 16강 이변에 국가공휴일 선포"
        },
        {
          "source": "yna",
          "title": "[월드컵] 독일 총리 \"대단한 경기\" 위로했다가 여론 뭇매"
        }
      ]
    },
    {
      "term": "경기",
      "total": 4,
      "sourceCount": 2,
      "sources": [
        "yna",
        "donga"
      ],
      "examples": [
        {
          "source": "yna",
          "title": "[월드컵] 독일 총리 \"대단한 경기\" 위로했다가 뭇매(종합)"
        },
        {
          "source": "yna",
          "title": "북중미 월드컵에도 뜨거운 프로야구…역대 최소 경기 700만 관중"
        },
        {
          "source": "yna",
          "title": "[월드컵] 독일 총리 \"대단한 경기\" 위로했다가 여론 뭇매"
        }
      ]
    },
    {
      "term": "유럽",
      "total": 4,
      "sourceCount": 2,
      "sources": [
        "yna",
        "mk"
      ],
      "examples": [
        {
          "source": "yna",
          "title": "국경 잠그는 유럽…이민자에 문 여는 스페인, 100만명 합법화 신청"
        },
        {
          "source": "yna",
          "title": "식지 않는 유럽…헝가리 42도 '신기록', 이탈리아 5명 사망"
        },
        {
          "source": "yna",
          "title": "유럽 재무장 가속…영국도 국방비 30조원 증액"
        }
      ]
    },
    {
      "term": "불참",
      "total": 4,
      "sourceCount": 2,
      "sources": [
        "yna",
        "hani"
      ],
      "examples": [
        {
          "source": "yna",
          "title": "아르헨 밀레이, 메르코수르 정상회의 불참…국내 정치일정 택해"
        },
        {
          "source": "yna",
          "title": "한성숙 총리 후보자 임명동의안 與주도 국회 통과…국힘 불참"
        },
        {
          "source": "yna",
          "title": "법사 포함 10개 상임위·예결위원장 與주도 선출…국힘 표결 불참(종합)"
        }
      ]
    },
    {
      "term": "회담",
      "total": 4,
      "sourceCount": 2,
      "sources": [
        "yna",
        "hani"
      ],
      "examples": [
        {
          "source": "yna",
          "title": "이란 외무부 \"향후 며칠간 'MOU 이행' 평가 후 최종 회담 결정\""
        },
        {
          "source": "yna",
          "title": "카타르 \"美특사, 중재자와 회동…이란과 고위급 회담 계획 없어\"(종합)"
        },
        {
          "source": "yna",
          "title": "카타르 \"美특사, 중재자와 회동…이란과 고위급 회담 계획 없어\""
        }
      ]
    },
    {
      "term": "김도영",
      "total": 4,
      "sourceCount": 2,
      "sources": [
        "yna",
        "donga"
      ],
      "examples": [
        {
          "source": "yna",
          "title": "KIA 김도영 24·25홈런 '쾅쾅'…키움 안우진 5⅔이닝 11탈삼진(종합2보)"
        },
        {
          "source": "yna",
          "title": "KIA 김도영 24·25홈런 '쾅쾅'…키움 안우진 5⅔이닝 11탈삼진(종합)"
        },
        {
          "source": "yna",
          "title": "뜨거운 김도영, 24·25호 폭발…홈런 단독 1위 도약(종합)"
        }
      ]
    },
    {
      "term": "카타르",
      "total": 4,
      "sourceCount": 2,
      "sources": [
        "yna",
        "hani"
      ],
      "examples": [
        {
          "source": "yna",
          "title": "카타르 \"美특사, 중재자와 회동…이란과 고위급 회담 계획 없어\"(종합)"
        },
        {
          "source": "yna",
          "title": "카타르 \"美특사, 중재자와 회동…이란과 고위급 회담 계획 없어\""
        },
        {
          "source": "hani",
          "title": "호르무즈 충돌 뒤, 미-이란 카타르 모인다…얼굴 맞대진 않아"
        }
      ]
    },
    {
      "term": "후반기",
      "total": 4,
      "sourceCount": 2,
      "sources": [
        "khan",
        "hani"
      ],
      "examples": [
        {
          "source": "khan",
          "title": "국회 후반기 법사위원장에 서영교…10개 상임위·예결위원장 민주당으로"
        },
        {
          "source": "khan",
          "title": "한성숙 총리 임명동의안 통과…22대 후반기 국회 11개 위원회 위원장도 여당 주도 의결"
        },
        {
          "source": "khan",
          "title": "후반기 법사위원장에 서영교…정무위·재경위도 민주당에"
        }
      ]
    },
    {
      "term": "제주",
      "total": 3,
      "sourceCount": 2,
      "sources": [
        "yna",
        "mk"
      ],
      "examples": [
        {
          "source": "yna",
          "title": "서귀포시중산간 등 제주 5곳 호우주의보"
        },
        {
          "source": "yna",
          "title": "[날씨] 내일 남부·제주 강한 비…수도권·강원은 소나기"
        },
        {
          "source": "mk",
          "title": "“내일 출근길 우산 챙기세요”…남부·제주 강한 비에 최고기온 33도"
        }
      ]
    },
    {
      "term": "참여",
      "total": 3,
      "sourceCount": 2,
      "sources": [
        "yna",
        "mk"
      ],
      "examples": [
        {
          "source": "yna",
          "title": "美대법 \"트랜스젠더의 여학생 스포츠팀 참여 금지 합당\" 판결(종합)"
        },
        {
          "source": "yna",
          "title": "美대법 \"트랜스젠더의 여학생 스포츠팀 참여 금지 합당\" 판결"
        },
        {
          "source": "mk",
          "title": "삼성전자, 한화 참여...글로벌 스테이블코인 연합체 출격"
        }
      ]
    },
    {
      "term": "쾅쾅",
      "total": 3,
      "sourceCount": 2,
      "sources": [
        "yna",
        "donga"
      ],
      "examples": [
        {
          "source": "yna",
          "title": "KIA 김도영 24·25홈런 '쾅쾅'…키움 안우진 5⅔이닝 11탈삼진(종합2보)"
        },
        {
          "source": "yna",
          "title": "KIA 김도영 24·25홈런 '쾅쾅'…키움 안우진 5⅔이닝 11탈삼진(종합)"
        },
        {
          "source": "donga",
          "title": "‘김도영 홈런 쾅쾅·김선빈 타이거즈 최다 안타’ KIA, SSG 완파…키움, 선두 LG 제압"
        }
      ]
    },
    {
      "term": "보이콧",
      "total": 3,
      "sourceCount": 2,
      "sources": [
        "yna",
        "mk"
      ],
      "examples": [
        {
          "source": "yna",
          "title": "한성숙 총리 후보 임명동의안 與주도 국회 통과…국힘 보이콧(종합)"
        },
        {
          "source": "yna",
          "title": "[속보] 한성숙 총리 후보 인준안 국회 통과…국힘은 표결 보이콧"
        },
        {
          "source": "mk",
          "title": "[속보] 한성숙 총리 후보 인준안 국회 통과…국힘은 표결 보이콧"
        }
      ]
    },
    {
      "term": "표결",
      "total": 3,
      "sourceCount": 2,
      "sources": [
        "yna",
        "mk"
      ],
      "examples": [
        {
          "source": "yna",
          "title": "[속보] 한성숙 총리 후보 인준안 국회 통과…국힘은 표결 보이콧"
        },
        {
          "source": "yna",
          "title": "법사 포함 10개 상임위·예결위원장 與주도 선출…국힘 표결 불참(종합)"
        },
        {
          "source": "mk",
          "title": "[속보] 한성숙 총리 후보 인준안 국회 통과…국힘은 표결 보이콧"
        }
      ]
    },
    {
      "term": "호남",
      "total": 3,
      "sourceCount": 2,
      "sources": [
        "yna",
        "hani"
      ],
      "examples": [
        {
          "source": "yna",
          "title": "[프로필] 서삼석 농해수위원장…지방 행정 아우른 '호남 풀뿌리'"
        },
        {
          "source": "hani",
          "title": "‘이재명 메가프로젝트’ 호남 반도체…50년 불균형 바로잡나 [전문가 리포트]"
        },
        {
          "source": "hani",
          "title": "호남 소외가 만든 ‘기회’…땅값 낮아 반도체 투자, 청년들은 기대"
        }
      ]
    },
    {
      "term": "특사",
      "total": 3,
      "sourceCount": 2,
      "sources": [
        "yna",
        "hani"
      ],
      "examples": [
        {
          "source": "yna",
          "title": "카타르 \"美특사, 중재자와 회동…이란과 고위급 회담 계획 없어\"(종합)"
        },
        {
          "source": "yna",
          "title": "카타르 \"美특사, 중재자와 회동…이란과 고위급 회담 계획 없어\""
        },
        {
          "source": "hani",
          "title": "“미 특사, 카타르 중재자와 회동…이란과 고위급 회담 계획 없다”"
        }
      ]
    },
    {
      "term": "중재자와",
      "total": 3,
      "sourceCount": 2,
      "sources": [
        "yna",
        "hani"
      ],
      "examples": [
        {
          "source": "yna",
          "title": "카타르 \"美특사, 중재자와 회동…이란과 고위급 회담 계획 없어\"(종합)"
        },
        {
          "source": "yna",
          "title": "카타르 \"美특사, 중재자와 회동…이란과 고위급 회담 계획 없어\""
        },
        {
          "source": "hani",
          "title": "“미 특사, 카타르 중재자와 회동…이란과 고위급 회담 계획 없다”"
        }
      ]
    },
    {
      "term": "회동",
      "total": 3,
      "sourceCount": 2,
      "sources": [
        "yna",
        "hani"
      ],
      "examples": [
        {
          "source": "yna",
          "title": "카타르 \"美특사, 중재자와 회동…이란과 고위급 회담 계획 없어\"(종합)"
        },
        {
          "source": "yna",
          "title": "카타르 \"美특사, 중재자와 회동…이란과 고위급 회담 계획 없어\""
        },
        {
          "source": "hani",
          "title": "“미 특사, 카타르 중재자와 회동…이란과 고위급 회담 계획 없다”"
        }
      ]
    },
    {
      "term": "이란과",
      "total": 3,
      "sourceCount": 2,
      "sources": [
        "yna",
        "hani"
      ],
      "examples": [
        {
          "source": "yna",
          "title": "카타르 \"美특사, 중재자와 회동…이란과 고위급 회담 계획 없어\"(종합)"
        },
        {
          "source": "yna",
          "title": "카타르 \"美특사, 중재자와 회동…이란과 고위급 회담 계획 없어\""
        },
        {
          "source": "hani",
          "title": "“미 특사, 카타르 중재자와 회동…이란과 고위급 회담 계획 없다”"
        }
      ]
    },
    {
      "term": "고위급",
      "total": 3,
      "sourceCount": 2,
      "sources": [
        "yna",
        "hani"
      ],
      "examples": [
        {
          "source": "yna",
          "title": "카타르 \"美특사, 중재자와 회동…이란과 고위급 회담 계획 없어\"(종합)"
        },
        {
          "source": "yna",
          "title": "카타르 \"美특사, 중재자와 회동…이란과 고위급 회담 계획 없어\""
        },
        {
          "source": "hani",
          "title": "“미 특사, 카타르 중재자와 회동…이란과 고위급 회담 계획 없다”"
        }
      ]
    },
    {
      "term": "계획",
      "total": 3,
      "sourceCount": 2,
      "sources": [
        "yna",
        "hani"
      ],
      "examples": [
        {
          "source": "yna",
          "title": "카타르 \"美특사, 중재자와 회동…이란과 고위급 회담 계획 없어\"(종합)"
        },
        {
          "source": "yna",
          "title": "카타르 \"美특사, 중재자와 회동…이란과 고위급 회담 계획 없어\""
        },
        {
          "source": "hani",
          "title": "“미 특사, 카타르 중재자와 회동…이란과 고위급 회담 계획 없다”"
        }
      ]
    },
    {
      "term": "없어",
      "total": 3,
      "sourceCount": 2,
      "sources": [
        "yna",
        "mk"
      ],
      "examples": [
        {
          "source": "yna",
          "title": "카타르 \"美특사, 중재자와 회동…이란과 고위급 회담 계획 없어\"(종합)"
        },
        {
          "source": "yna",
          "title": "카타르 \"美특사, 중재자와 회동…이란과 고위급 회담 계획 없어\""
        },
        {
          "source": "mk",
          "title": "\"자유와 신뢰로 일군 美경제 … 부패한 정치와 함께 갈 수 없어\""
        }
      ]
    },
    {
      "term": "인상",
      "total": 3,
      "sourceCount": 2,
      "sources": [
        "yna",
        "mk"
      ],
      "examples": [
        {
          "source": "yna",
          "title": "日도쿄, 숙박세 3% 정률제로 인상 확정…'오버투어리즘' 대응"
        },
        {
          "source": "mk",
          "title": "\"삼전닉스에 박탈감\"… 공무원 노조 임금 7.1% 인상 요구"
        },
        {
          "source": "mk",
          "title": "“삼전닉스 성과급 잔치에 세수 늘잖아”…공무원 노조, 임금 7.1% 인상 요구"
        }
      ]
    },
    {
      "term": "최저임금",
      "total": 3,
      "sourceCount": 2,
      "sources": [
        "yna",
        "hani"
      ],
      "examples": [
        {
          "source": "yna",
          "title": "최저임금, 노 1만1천900원 vs 사 1만360원…격차 1천540원(종합)"
        },
        {
          "source": "yna",
          "title": "[속보] 노동계 1만1천900원·경영계 1만360원…최저임금 2차수정안"
        },
        {
          "source": "hani",
          "title": "최저임금 2차 수정안 낸 노사…1만1900원 vs 1만360원"
        }
      ]
    },
    {
      "term": "신임",
      "total": 3,
      "sourceCount": 2,
      "sources": [
        "yna",
        "donga"
      ],
      "examples": [
        {
          "source": "yna",
          "title": "경인사연, 국토·통일·노동연구원 신임 원장 선임(종합)"
        },
        {
          "source": "donga",
          "title": "IBK투자증권 최광진 신임 대표 선임"
        },
        {
          "source": "donga",
          "title": "[프로필] 한성숙 신임 국무총리…AI·플랫폼 전문가에서 국정 2인자로"
        }
      ]
    },
    {
      "term": "선임",
      "total": 3,
      "sourceCount": 2,
      "sources": [
        "yna",
        "donga"
      ],
      "examples": [
        {
          "source": "yna",
          "title": "경인사연, 국토·통일·노동연구원 신임 원장 선임(종합)"
        },
        {
          "source": "donga",
          "title": "NH투자증권 새 경영체제 출범… 신재욱-배광수 각자 대표 선임"
        },
        {
          "source": "donga",
          "title": "IBK투자증권 최광진 신임 대표 선임"
        }
      ]
    },
    {
      "term": "삼성전기",
      "total": 3,
      "sourceCount": 2,
      "sources": [
        "donga",
        "mk"
      ],
      "examples": [
        {
          "source": "donga",
          "title": "삼성전기, 빅테크에 4500억 규모 MLCC 공급"
        },
        {
          "source": "mk",
          "title": "삼성전기 불기둥 이유 있었네…글로벌빅테크에 4500억 MLCC 공급"
        },
        {
          "source": "mk",
          "title": "[인기검색TOP5] 에브리봇, 지니너스, 현대무벡스, 삼성전기, KB금융"
        }
      ]
    },
    {
      "term": "신동빈",
      "total": 3,
      "sourceCount": 2,
      "sources": [
        "donga",
        "mk"
      ],
      "examples": [
        {
          "source": "donga",
          "title": "신동빈 ‘원롯데’ 전략, 식품사업부터 속도 낸다"
        },
        {
          "source": "mk",
          "title": "“보고서는 AI가 쓰고 직원은 판단 위주로”…롯데 신동빈, 그룹 DNA 바꾼다"
        },
        {
          "source": "mk",
          "title": "신동빈 ‘원롯데’ 전략 통했다...한일 식품사 첫 통합법인 출범"
        }
      ]
    },
    {
      "term": "전략",
      "total": 3,
      "sourceCount": 2,
      "sources": [
        "donga",
        "mk"
      ],
      "examples": [
        {
          "source": "donga",
          "title": "신동빈 ‘원롯데’ 전략, 식품사업부터 속도 낸다"
        },
        {
          "source": "donga",
          "title": "AI 수출통제 시대, 한국의 디지털 전략 자산은?[기고/박성호]"
        },
        {
          "source": "mk",
          "title": "신동빈 ‘원롯데’ 전략 통했다...한일 식품사 첫 통합법인 출범"
        }
      ]
    },
    {
      "term": "요구",
      "total": 3,
      "sourceCount": 2,
      "sources": [
        "donga",
        "mk"
      ],
      "examples": [
        {
          "source": "donga",
          "title": "“100만원 시작해 5만원까지”…직장 상사의 반복된 금전 대출 요구 어쩌나"
        },
        {
          "source": "mk",
          "title": "\"삼전닉스에 박탈감\"… 공무원 노조 임금 7.1% 인상 요구"
        },
        {
          "source": "mk",
          "title": "“삼전닉스 성과급 잔치에 세수 늘잖아”…공무원 노조, 임금 7.1% 인상 요구"
        }
      ]
    },
    {
      "term": "동탄",
      "total": 3,
      "sourceCount": 2,
      "sources": [
        "khan",
        "mk"
      ],
      "examples": [
        {
          "source": "khan",
          "title": "이제서야…동탄·기흥·구리, 규제지역·토허구역 지정"
        },
        {
          "source": "mk",
          "title": "동탄·기흥 등 규제지역 추가 지정에...국힘 “곳곳 풍선효과…벌칙은 국민이 받는 꼴”"
        },
        {
          "source": "mk",
          "title": "동탄·기흥·구리 '핀셋 3중규제'"
        }
      ]
    },
    {
      "term": "기흥",
      "total": 3,
      "sourceCount": 2,
      "sources": [
        "khan",
        "mk"
      ],
      "examples": [
        {
          "source": "khan",
          "title": "이제서야…동탄·기흥·구리, 규제지역·토허구역 지정"
        },
        {
          "source": "mk",
          "title": "동탄·기흥 등 규제지역 추가 지정에...국힘 “곳곳 풍선효과…벌칙은 국민이 받는 꼴”"
        },
        {
          "source": "mk",
          "title": "동탄·기흥·구리 '핀셋 3중규제'"
        }
      ]
    },
    {
      "term": "상징",
      "total": 3,
      "sourceCount": 2,
      "sources": [
        "mk",
        "hani"
      ],
      "examples": [
        {
          "source": "mk",
          "title": "‘스벅 논란’ 얼마나 됐다고...하다하다 계엄군 상징 군화까지 걸렸다"
        },
        {
          "source": "mk",
          "title": "\"번영 상징 美, 문제는 고삐풀린 자본주의\""
        },
        {
          "source": "hani",
          "title": "헌법에 막힌 트럼프의 ‘반이민 상징’…보수 대법원, 출생 시민권 지켜내"
        }
      ]
    },
    {
      "term": "협상",
      "total": 2,
      "sourceCount": 2,
      "sources": [
        "yna",
        "khan"
      ],
      "examples": [
        {
          "source": "yna",
          "title": "쿠바 \"미국과 협상 진전 없었다\"…美봉쇄 논의 유엔총회 요청"
        },
        {
          "source": "khan",
          "title": "실수로 김일성 사진 찢은 북 대표 “남측이 도발”…막말·‘외모 비하’ 발언까지 쏟아진 비핵화 협상"
        }
      ]
    },
    {
      "term": "스페이스",
      "total": 2,
      "sourceCount": 2,
      "sources": [
        "yna",
        "khan"
      ],
      "examples": [
        {
          "source": "yna",
          "title": "\"미래에셋, 스페이스X 공모주 수요파악을 주문 접수로 오해\""
        },
        {
          "source": "khan",
          "title": "로켓랩, 스페이스X에 도전장…위성·통신 ‘이리듐’ 품는다"
        }
      ]
    },
    {
      "term": "의결",
      "total": 2,
      "sourceCount": 2,
      "sources": [
        "yna",
        "khan"
      ],
      "examples": [
        {
          "source": "yna",
          "title": "전남광주특별시의회, '반도체 지원 조례' 1호 안건 의결"
        },
        {
          "source": "khan",
          "title": "한성숙 총리 임명동의안 통과…22대 후반기 국회 11개 위원회 위원장도 여당 주도 의결"
        }
      ]
    },
    {
      "term": "초대",
      "total": 2,
      "sourceCount": 2,
      "sources": [
        "yna",
        "hani"
      ],
      "examples": [
        {
          "source": "yna",
          "title": "초대 전남광주통합특별시의희 의장에 송형곤 의원 선출"
        },
        {
          "source": "hani",
          "title": "초대 민선 허경만 전 전남도지사 “내가 실패한 통합 성공해 감회 깊다”"
        }
      ]
    },
    {
      "term": "유지된다",
      "total": 2,
      "sourceCount": 2,
      "sources": [
        "yna",
        "donga"
      ],
      "examples": [
        {
          "source": "yna",
          "title": "美 '출생시민권' 유지된다…대법원, 트럼프 이민정책에 제동(종합)"
        },
        {
          "source": "donga",
          "title": "美출생시민권 유지된다…보수성향 대법원이 트럼프 제동"
        }
      ]
    },
    {
      "term": "전남",
      "total": 2,
      "sourceCount": 2,
      "sources": [
        "yna",
        "hani"
      ],
      "examples": [
        {
          "source": "yna",
          "title": "진도 등 전남 4곳 호우주의보"
        },
        {
          "source": "hani",
          "title": "반도체 품고 하나 된 전남·광주…수도권 견줄 ‘300조 경제권’ 목표"
        }
      ]
    },
    {
      "term": "파라과이",
      "total": 2,
      "sourceCount": 2,
      "sources": [
        "yna",
        "khan"
      ],
      "examples": [
        {
          "source": "yna",
          "title": "[월드컵] 파라과이, 독일 꺾고 16강 이변에 국가공휴일 선포"
        },
        {
          "source": "khan",
          "title": "[2026 북중미 월드컵] 16강 진출한 파라과이, 임시 공휴일 선포"
        }
      ]
    },
    {
      "term": "선포",
      "total": 2,
      "sourceCount": 2,
      "sources": [
        "yna",
        "khan"
      ],
      "examples": [
        {
          "source": "yna",
          "title": "[월드컵] 파라과이, 독일 꺾고 16강 이변에 국가공휴일 선포"
        },
        {
          "source": "khan",
          "title": "[2026 북중미 월드컵] 16강 진출한 파라과이, 임시 공휴일 선포"
        }
      ]
    },
    {
      "term": "탈북",
      "total": 2,
      "sourceCount": 2,
      "sources": [
        "yna",
        "donga"
      ],
      "examples": [
        {
          "source": "yna",
          "title": "탈북 여성의 삶 그린 덴마크 감독 \"동정이나 규정 말았으면\""
        },
        {
          "source": "donga",
          "title": "“韓 정착 탈북 여성 용기에 보답하고자 이 영화 완성시켜”"
        }
      ]
    },
    {
      "term": "찾은",
      "total": 2,
      "sourceCount": 2,
      "sources": [
        "yna",
        "mk"
      ],
      "examples": [
        {
          "source": "yna",
          "title": "마지막 날 경찰·소방 찾은 金총리…\"후임 총리도 챙겨주시길\""
        },
        {
          "source": "mk",
          "title": "[포토] 연이틀 반도체 행보 … 전남광주 찾은 李"
        }
      ]
    },
    {
      "term": "경험",
      "total": 2,
      "sourceCount": 2,
      "sources": [
        "yna",
        "donga"
      ],
      "examples": [
        {
          "source": "yna",
          "title": "北中, 평양서 '당 건설 경험 교류회'…\"층위별 우호교류 확대\""
        },
        {
          "source": "donga",
          "title": "랄랄, 위고비·마운자로 부작용 경험…“위아래로 뿜었다”"
        }
      ]
    },
    {
      "term": "임명안",
      "total": 2,
      "sourceCount": 2,
      "sources": [
        "yna",
        "hani"
      ],
      "examples": [
        {
          "source": "yna",
          "title": "李대통령, 한성숙 총리 임명안 재가…역대 두번째 여성총리 탄생"
        },
        {
          "source": "hani",
          "title": "이 대통령, 한성숙 국무총리 임명안 재가"
        }
      ]
    },
    {
      "term": "재가",
      "total": 2,
      "sourceCount": 2,
      "sources": [
        "yna",
        "hani"
      ],
      "examples": [
        {
          "source": "yna",
          "title": "李대통령, 한성숙 총리 임명안 재가…역대 두번째 여성총리 탄생"
        },
        {
          "source": "hani",
          "title": "이 대통령, 한성숙 국무총리 임명안 재가"
        }
      ]
    },
    {
      "term": "호르무즈",
      "total": 2,
      "sourceCount": 2,
      "sources": [
        "yna",
        "hani"
      ],
      "examples": [
        {
          "source": "yna",
          "title": "\"호르무즈 공급차질 시뮬레이션 해보니…한국 8월까진 잘 관리\""
        },
        {
          "source": "hani",
          "title": "호르무즈 충돌 뒤, 미-이란 카타르 모인다…얼굴 맞대진 않아"
        }
      ]
    },
    {
      "term": "관리",
      "total": 2,
      "sourceCount": 2,
      "sources": [
        "yna",
        "khan"
      ],
      "examples": [
        {
          "source": "yna",
          "title": "\"호르무즈 공급차질 시뮬레이션 해보니…한국 8월까진 잘 관리\""
        },
        {
          "source": "khan",
          "title": "법무부, ‘관봉권 띠지 부실 관리’ 최재현 검사에 감봉 1개월"
        }
      ]
    },
    {
      "term": "장관",
      "total": 2,
      "sourceCount": 2,
      "sources": [
        "yna",
        "mk"
      ],
      "examples": [
        {
          "source": "yna",
          "title": "유리천장 깨는 교황의 인사…이탈리아 수녀, 교황청 장관 됐다"
        },
        {
          "source": "mk",
          "title": "전화번호 공개한 정성호 법무부 장관…스토킹 피해에도 즉각 응답했다"
        }
      ]
    },
    {
      "term": "북중미",
      "total": 2,
      "sourceCount": 2,
      "sources": [
        "yna",
        "khan"
      ],
      "examples": [
        {
          "source": "yna",
          "title": "북중미 월드컵에도 뜨거운 프로야구…역대 최소 경기 700만 관중"
        },
        {
          "source": "khan",
          "title": "[2026 북중미 월드컵] 16강 진출한 파라과이, 임시 공휴일 선포"
        }
      ]
    }
  ],
  "singleSourceTop": [
    {
      "term": "안우진",
      "total": 5,
      "sourceCount": 1,
      "sources": [
        "yna"
      ],
      "examples": [
        {
          "source": "yna",
          "title": "KIA 김도영 24·25홈런 '쾅쾅'…키움 안우진 5⅔이닝 11탈삼진(종합2보)"
        },
        {
          "source": "yna",
          "title": "키움 안우진, LG전 5⅔이닝 11K 역투 \"예전 모습 찾아가고 있어\"(종합)"
        },
        {
          "source": "yna",
          "title": "KIA 김도영 24·25홈런 '쾅쾅'…키움 안우진 5⅔이닝 11탈삼진(종합)"
        }
      ]
    },
    {
      "term": "호우주의보",
      "total": 4,
      "sourceCount": 1,
      "sources": [
        "yna"
      ],
      "examples": [
        {
          "source": "yna",
          "title": "제주시중산간·제주시서부에 호우주의보"
        },
        {
          "source": "yna",
          "title": "서귀포시중산간 등 제주 5곳 호우주의보"
        },
        {
          "source": "yna",
          "title": "진도 등 전남 4곳 호우주의보"
        }
      ]
    },
    {
      "term": "이닝",
      "total": 4,
      "sourceCount": 1,
      "sources": [
        "yna"
      ],
      "examples": [
        {
          "source": "yna",
          "title": "KIA 김도영 24·25홈런 '쾅쾅'…키움 안우진 5⅔이닝 11탈삼진(종합2보)"
        },
        {
          "source": "yna",
          "title": "키움 안우진, LG전 5⅔이닝 11K 역투 \"예전 모습 찾아가고 있어\"(종합)"
        },
        {
          "source": "yna",
          "title": "KIA 김도영 24·25홈런 '쾅쾅'…키움 안우진 5⅔이닝 11탈삼진(종합)"
        }
      ]
    },
    {
      "term": "이민정책에",
      "total": 3,
      "sourceCount": 1,
      "sources": [
        "yna"
      ],
      "examples": [
        {
          "source": "yna",
          "title": "美 '출생시민권' 유지된다…대법원, 트럼프 이민정책에 제동(종합)"
        },
        {
          "source": "yna",
          "title": "美대법, '출생시민권' 유지 판결…트럼프 이민정책에 제동"
        },
        {
          "source": "yna",
          "title": "[속보] 美대법원, '출생시민권 금지' 트럼프 이민정책에 제동"
        }
      ]
    },
    {
      "term": "대법",
      "total": 3,
      "sourceCount": 1,
      "sources": [
        "yna"
      ],
      "examples": [
        {
          "source": "yna",
          "title": "美대법 \"트랜스젠더의 여학생 스포츠팀 참여 금지 합당\" 판결(종합)"
        },
        {
          "source": "yna",
          "title": "美대법, '출생시민권' 유지 판결…트럼프 이민정책에 제동"
        },
        {
          "source": "yna",
          "title": "美대법 \"트랜스젠더의 여학생 스포츠팀 참여 금지 합당\" 판결"
        }
      ]
    },
    {
      "term": "금지",
      "total": 3,
      "sourceCount": 1,
      "sources": [
        "yna"
      ],
      "examples": [
        {
          "source": "yna",
          "title": "美대법 \"트랜스젠더의 여학생 스포츠팀 참여 금지 합당\" 판결(종합)"
        },
        {
          "source": "yna",
          "title": "美대법 \"트랜스젠더의 여학생 스포츠팀 참여 금지 합당\" 판결"
        },
        {
          "source": "yna",
          "title": "[속보] 美대법원, '출생시민권 금지' 트럼프 이민정책에 제동"
        }
      ]
    },
    {
      "term": "판결",
      "total": 3,
      "sourceCount": 1,
      "sources": [
        "yna"
      ],
      "examples": [
        {
          "source": "yna",
          "title": "美대법 \"트랜스젠더의 여학생 스포츠팀 참여 금지 합당\" 판결(종합)"
        },
        {
          "source": "yna",
          "title": "美대법, '출생시민권' 유지 판결…트럼프 이민정책에 제동"
        },
        {
          "source": "yna",
          "title": "美대법 \"트랜스젠더의 여학생 스포츠팀 참여 금지 합당\" 판결"
        }
      ]
    },
    {
      "term": "이탈리아",
      "total": 3,
      "sourceCount": 1,
      "sources": [
        "yna"
      ],
      "examples": [
        {
          "source": "yna",
          "title": "식지 않는 유럽…헝가리 42도 '신기록', 이탈리아 5명 사망"
        },
        {
          "source": "yna",
          "title": "유리천장 깨는 교황의 인사…이탈리아 수녀, 교황청 장관 됐다"
        },
        {
          "source": "yna",
          "title": "이탈리아, 고대 에트루리아 무덤 벽화 265억원에 샀다"
        }
      ]
    },
    {
      "term": "탈삼진",
      "total": 3,
      "sourceCount": 1,
      "sources": [
        "yna"
      ],
      "examples": [
        {
          "source": "yna",
          "title": "KIA 김도영 24·25홈런 '쾅쾅'…키움 안우진 5⅔이닝 11탈삼진(종합2보)"
        },
        {
          "source": "yna",
          "title": "KIA 김도영 24·25홈런 '쾅쾅'…키움 안우진 5⅔이닝 11탈삼진(종합)"
        },
        {
          "source": "yna",
          "title": "안우진, LG전 5⅔이닝 무실점 11K…1천69일만에 두자릿수 탈삼진"
        }
      ]
    },
    {
      "term": "출신",
      "total": 3,
      "sourceCount": 1,
      "sources": [
        "yna"
      ],
      "examples": [
        {
          "source": "yna",
          "title": "[프로필] 이재정 문체위원장…인권변호사 출신 3선"
        },
        {
          "source": "yna",
          "title": "[프로필] 김정호 기후노동위원장…참여정부 출신 영남 3선"
        },
        {
          "source": "yna",
          "title": "[프로필] 유동수 정무위원장…공인회계사 출신 경제통"
        }
      ]
    },
    {
      "term": "이유",
      "total": 3,
      "sourceCount": 1,
      "sources": [
        "mk"
      ],
      "examples": [
        {
          "source": "mk",
          "title": "“사관학교 입학성적 계속 낮아져”...안규백, 전군에 지휘서신 보낸 이유"
        },
        {
          "source": "mk",
          "title": "삼성전기 불기둥 이유 있었네…글로벌빅테크에 4500억 MLCC 공급"
        },
        {
          "source": "mk",
          "title": "“프랑스 폭염, 미국도 책임 있어”…파리 부시장이 직격한 이유"
        }
      ]
    },
    {
      "term": "유지",
      "total": 2,
      "sourceCount": 1,
      "sources": [
        "yna"
      ],
      "examples": [
        {
          "source": "yna",
          "title": "트럼프 \"출생시민권 유지, 큰 불행…의회입법으로 만회 가능\""
        },
        {
          "source": "yna",
          "title": "美대법, '출생시민권' 유지 판결…트럼프 이민정책에 제동"
        }
      ]
    },
    {
      "term": "대단한",
      "total": 2,
      "sourceCount": 1,
      "sources": [
        "yna"
      ],
      "examples": [
        {
          "source": "yna",
          "title": "[월드컵] 독일 총리 \"대단한 경기\" 위로했다가 뭇매(종합)"
        },
        {
          "source": "yna",
          "title": "[월드컵] 독일 총리 \"대단한 경기\" 위로했다가 여론 뭇매"
        }
      ]
    },
    {
      "term": "위로했다가",
      "total": 2,
      "sourceCount": 1,
      "sources": [
        "yna"
      ],
      "examples": [
        {
          "source": "yna",
          "title": "[월드컵] 독일 총리 \"대단한 경기\" 위로했다가 뭇매(종합)"
        },
        {
          "source": "yna",
          "title": "[월드컵] 독일 총리 \"대단한 경기\" 위로했다가 여론 뭇매"
        }
      ]
    },
    {
      "term": "뭇매",
      "total": 2,
      "sourceCount": 1,
      "sources": [
        "yna"
      ],
      "examples": [
        {
          "source": "yna",
          "title": "[월드컵] 독일 총리 \"대단한 경기\" 위로했다가 뭇매(종합)"
        },
        {
          "source": "yna",
          "title": "[월드컵] 독일 총리 \"대단한 경기\" 위로했다가 여론 뭇매"
        }
      ]
    },
    {
      "term": "전남광주통합특별시의",
      "total": 2,
      "sourceCount": 1,
      "sources": [
        "yna"
      ],
      "examples": [
        {
          "source": "yna",
          "title": "초대 전남광주통합특별시의희 의장에 송형곤 의원 선출"
        },
        {
          "source": "yna",
          "title": "전남광주통합특별시의회 본회의 0시 첫 개회…통합시대 열어"
        }
      ]
    },
    {
      "term": "트랜스젠더의",
      "total": 2,
      "sourceCount": 1,
      "sources": [
        "yna"
      ],
      "examples": [
        {
          "source": "yna",
          "title": "美대법 \"트랜스젠더의 여학생 스포츠팀 참여 금지 합당\" 판결(종합)"
        },
        {
          "source": "yna",
          "title": "美대법 \"트랜스젠더의 여학생 스포츠팀 참여 금지 합당\" 판결"
        }
      ]
    },
    {
      "term": "여학생",
      "total": 2,
      "sourceCount": 1,
      "sources": [
        "yna"
      ],
      "examples": [
        {
          "source": "yna",
          "title": "美대법 \"트랜스젠더의 여학생 스포츠팀 참여 금지 합당\" 판결(종합)"
        },
        {
          "source": "yna",
          "title": "美대법 \"트랜스젠더의 여학생 스포츠팀 참여 금지 합당\" 판결"
        }
      ]
    },
    {
      "term": "스포츠팀",
      "total": 2,
      "sourceCount": 1,
      "sources": [
        "yna"
      ],
      "examples": [
        {
          "source": "yna",
          "title": "美대법 \"트랜스젠더의 여학생 스포츠팀 참여 금지 합당\" 판결(종합)"
        },
        {
          "source": "yna",
          "title": "美대법 \"트랜스젠더의 여학생 스포츠팀 참여 금지 합당\" 판결"
        }
      ]
    },
    {
      "term": "합당",
      "total": 2,
      "sourceCount": 1,
      "sources": [
        "yna"
      ],
      "examples": [
        {
          "source": "yna",
          "title": "美대법 \"트랜스젠더의 여학생 스포츠팀 참여 금지 합당\" 판결(종합)"
        },
        {
          "source": "yna",
          "title": "美대법 \"트랜스젠더의 여학생 스포츠팀 참여 금지 합당\" 판결"
        }
      ]
    },
    {
      "term": "덴마크",
      "total": 2,
      "sourceCount": 1,
      "sources": [
        "yna"
      ],
      "examples": [
        {
          "source": "yna",
          "title": "푸틴 소유 추정 요트, 4년만에 포착…\"덴마크 해안 출몰\""
        },
        {
          "source": "yna",
          "title": "탈북 여성의 삶 그린 덴마크 감독 \"동정이나 규정 말았으면\""
        }
      ]
    },
    {
      "term": "사망",
      "total": 2,
      "sourceCount": 1,
      "sources": [
        "yna"
      ],
      "examples": [
        {
          "source": "yna",
          "title": "식지 않는 유럽…헝가리 42도 '신기록', 이탈리아 5명 사망"
        },
        {
          "source": "yna",
          "title": "폭염주의보 이틀째…서울에서 온열질환으로 1명 사망"
        }
      ]
    },
    {
      "term": "전남광주특별시",
      "total": 2,
      "sourceCount": 1,
      "sources": [
        "yna"
      ],
      "examples": [
        {
          "source": "yna",
          "title": "대한민국 1호 광역행정통합 '전남광주특별시' 출범"
        },
        {
          "source": "yna",
          "title": "전남광주특별시 구청장협의회장에 김이강 서구청장 선출"
        }
      ]
    },
    {
      "term": "소방",
      "total": 2,
      "sourceCount": 1,
      "sources": [
        "yna"
      ],
      "examples": [
        {
          "source": "yna",
          "title": "마지막 날 경찰·소방 찾은 金총리…\"후임 총리도 챙겨주시길\""
        },
        {
          "source": "yna",
          "title": "소방 역사상 첫 여성 소방정감 탄생"
        }
      ]
    },
    {
      "term": "탄생",
      "total": 2,
      "sourceCount": 1,
      "sources": [
        "yna"
      ],
      "examples": [
        {
          "source": "yna",
          "title": "李대통령, 한성숙 총리 임명안 재가…역대 두번째 여성총리 탄생"
        },
        {
          "source": "yna",
          "title": "소방 역사상 첫 여성 소방정감 탄생"
        }
      ]
    },
    {
      "term": "뜨거운",
      "total": 2,
      "sourceCount": 1,
      "sources": [
        "yna"
      ],
      "examples": [
        {
          "source": "yna",
          "title": "북중미 월드컵에도 뜨거운 프로야구…역대 최소 경기 700만 관중"
        },
        {
          "source": "yna",
          "title": "뜨거운 김도영, 24·25호 폭발…홈런 단독 1위 도약(종합)"
        }
      ]
    },
    {
      "term": "내달부터",
      "total": 2,
      "sourceCount": 1,
      "sources": [
        "yna"
      ],
      "examples": [
        {
          "source": "yna",
          "title": "EU, 내달부터 소액 소포에 3유로 관세…쉬인·테무 등 겨냥(종합)"
        },
        {
          "source": "yna",
          "title": "EU, 내달부터 소액 소포에 3유로 관세…쉬인·테무 등 겨냥"
        }
      ]
    },
    {
      "term": "소액",
      "total": 2,
      "sourceCount": 1,
      "sources": [
        "yna"
      ],
      "examples": [
        {
          "source": "yna",
          "title": "EU, 내달부터 소액 소포에 3유로 관세…쉬인·테무 등 겨냥(종합)"
        },
        {
          "source": "yna",
          "title": "EU, 내달부터 소액 소포에 3유로 관세…쉬인·테무 등 겨냥"
        }
      ]
    },
    {
      "term": "소포에",
      "total": 2,
      "sourceCount": 1,
      "sources": [
        "yna"
      ],
      "examples": [
        {
          "source": "yna",
          "title": "EU, 내달부터 소액 소포에 3유로 관세…쉬인·테무 등 겨냥(종합)"
        },
        {
          "source": "yna",
          "title": "EU, 내달부터 소액 소포에 3유로 관세…쉬인·테무 등 겨냥"
        }
      ]
    },
    {
      "term": "유로",
      "total": 2,
      "sourceCount": 1,
      "sources": [
        "yna"
      ],
      "examples": [
        {
          "source": "yna",
          "title": "EU, 내달부터 소액 소포에 3유로 관세…쉬인·테무 등 겨냥(종합)"
        },
        {
          "source": "yna",
          "title": "EU, 내달부터 소액 소포에 3유로 관세…쉬인·테무 등 겨냥"
        }
      ]
    },
    {
      "term": "관세",
      "total": 2,
      "sourceCount": 1,
      "sources": [
        "yna"
      ],
      "examples": [
        {
          "source": "yna",
          "title": "EU, 내달부터 소액 소포에 3유로 관세…쉬인·테무 등 겨냥(종합)"
        },
        {
          "source": "yna",
          "title": "EU, 내달부터 소액 소포에 3유로 관세…쉬인·테무 등 겨냥"
        }
      ]
    },
    {
      "term": "쉬인",
      "total": 2,
      "sourceCount": 1,
      "sources": [
        "yna"
      ],
      "examples": [
        {
          "source": "yna",
          "title": "EU, 내달부터 소액 소포에 3유로 관세…쉬인·테무 등 겨냥(종합)"
        },
        {
          "source": "yna",
          "title": "EU, 내달부터 소액 소포에 3유로 관세…쉬인·테무 등 겨냥"
        }
      ]
    },
    {
      "term": "테무",
      "total": 2,
      "sourceCount": 1,
      "sources": [
        "yna"
      ],
      "examples": [
        {
          "source": "yna",
          "title": "EU, 내달부터 소액 소포에 3유로 관세…쉬인·테무 등 겨냥(종합)"
        },
        {
          "source": "yna",
          "title": "EU, 내달부터 소액 소포에 3유로 관세…쉬인·테무 등 겨냥"
        }
      ]
    },
    {
      "term": "겨냥",
      "total": 2,
      "sourceCount": 1,
      "sources": [
        "yna"
      ],
      "examples": [
        {
          "source": "yna",
          "title": "EU, 내달부터 소액 소포에 3유로 관세…쉬인·테무 등 겨냥(종합)"
        },
        {
          "source": "yna",
          "title": "EU, 내달부터 소액 소포에 3유로 관세…쉬인·테무 등 겨냥"
        }
      ]
    },
    {
      "term": "법사",
      "total": 2,
      "sourceCount": 1,
      "sources": [
        "yna"
      ],
      "examples": [
        {
          "source": "yna",
          "title": "법사 포함 10개 상임위·예결위원장 與주도 선출…국힘 표결 불참(종합)"
        },
        {
          "source": "yna",
          "title": "법사 포함 10개 상임위·예결위원장 與주도 선출…국힘 반발"
        }
      ]
    },
    {
      "term": "포함",
      "total": 2,
      "sourceCount": 1,
      "sources": [
        "yna"
      ],
      "examples": [
        {
          "source": "yna",
          "title": "법사 포함 10개 상임위·예결위원장 與주도 선출…국힘 표결 불참(종합)"
        },
        {
          "source": "yna",
          "title": "법사 포함 10개 상임위·예결위원장 與주도 선출…국힘 반발"
        }
      ]
    },
    {
      "term": "우려",
      "total": 2,
      "sourceCount": 1,
      "sources": [
        "yna"
      ],
      "examples": [
        {
          "source": "yna",
          "title": "민주콩고 에볼라 사망자 보름새 2배…\"5조원대 경제 손실 우려\""
        },
        {
          "source": "yna",
          "title": "허위조작정보 규제 내달 7일 시행…기대와 우려 교차"
        }
      ]
    },
    {
      "term": "부고",
      "total": 2,
      "sourceCount": 1,
      "sources": [
        "yna"
      ],
      "examples": [
        {
          "source": "yna",
          "title": "[부고] 이찬기(강원대 명예교수)씨 별세"
        },
        {
          "source": "yna",
          "title": "[부고] 전병근(치안문제연구소 수석연구위원)씨 부친상"
        }
      ]
    },
    {
      "term": "갔다",
      "total": 2,
      "sourceCount": 1,
      "sources": [
        "donga"
      ],
      "examples": [
        {
          "source": "donga",
          "title": "“수영장 갔다 온 후로 귀가 먹먹”…‘이 질환’ 신호"
        },
        {
          "source": "donga",
          "title": "‘귀한가족’ 신지♥문원 “신혼여행 못 갔다”…경주로 ‘허니문원’"
        }
      ]
    },
    {
      "term": "속도",
      "total": 2,
      "sourceCount": 1,
      "sources": [
        "donga"
      ],
      "examples": [
        {
          "source": "donga",
          "title": "LG전자, CEO 직속 ‘로보틱스’ 조직 신설… 피지컬AI 육성 속도"
        },
        {
          "source": "donga",
          "title": "신동빈 ‘원롯데’ 전략, 식품사업부터 속도 낸다"
        }
      ]
    },
    {
      "term": "투자증권",
      "total": 2,
      "sourceCount": 1,
      "sources": [
        "donga"
      ],
      "examples": [
        {
          "source": "donga",
          "title": "NH투자증권 새 경영체제 출범… 신재욱-배광수 각자 대표 선임"
        },
        {
          "source": "donga",
          "title": "IBK투자증권 최광진 신임 대표 선임"
        }
      ]
    },
    {
      "term": "지정",
      "total": 2,
      "sourceCount": 1,
      "sources": [
        "khan"
      ],
      "examples": [
        {
          "source": "khan",
          "title": "이제서야…동탄·기흥·구리, 규제지역·토허구역 지정"
        },
        {
          "source": "khan",
          "title": "앰코도 1조 들여 광주에 ‘첨단 패키징 공장’ 증설…정부, 혁신지원단·메가특구 지정 등 총력 뒷받침"
        }
      ]
    },
    {
      "term": "법사위원장에",
      "total": 2,
      "sourceCount": 1,
      "sources": [
        "khan"
      ],
      "examples": [
        {
          "source": "khan",
          "title": "국회 후반기 법사위원장에 서영교…10개 상임위·예결위원장 민주당으로"
        },
        {
          "source": "khan",
          "title": "후반기 법사위원장에 서영교…정무위·재경위도 민주당에"
        }
      ]
    },
    {
      "term": "여당",
      "total": 2,
      "sourceCount": 1,
      "sources": [
        "khan"
      ],
      "examples": [
        {
          "source": "khan",
          "title": "한성숙 총리 임명동의안, 여당 주도로 통과"
        },
        {
          "source": "khan",
          "title": "한성숙 총리 임명동의안 통과…22대 후반기 국회 11개 위원회 위원장도 여당 주도 의결"
        }
      ]
    },
    {
      "term": "시간",
      "total": 2,
      "sourceCount": 1,
      "sources": [
        "khan"
      ],
      "examples": [
        {
          "source": "khan",
          "title": "팹 건설부터 인프라 구축까지…이제 ‘슈퍼 패스트트랙’의 시간"
        },
        {
          "source": "khan",
          "title": "1주일 육아휴직도 가능…외환시장 ‘24시간 거래’ 시대 열린다[하반기 달라지는 것들]"
        }
      ]
    },
    {
      "term": "숙제",
      "total": 2,
      "sourceCount": 1,
      "sources": [
        "khan"
      ],
      "examples": [
        {
          "source": "khan",
          "title": "‘탈 경부축’ 반도체 생태계…전향적 시도, 균형발전 체감은 숙제"
        },
        {
          "source": "khan",
          "title": "‘청년 고용 눈치보기’ 정년 연장 숙제, 결국 하반기로 미뤘다"
        }
      ]
    },
    {
      "term": "원유",
      "total": 2,
      "sourceCount": 1,
      "sources": [
        "khan"
      ],
      "examples": [
        {
          "source": "khan",
          "title": "공공차량 2부제 해제…원유 수급 숨통, 석 달 만에 정상화"
        },
        {
          "source": "khan",
          "title": "원유 수급 긴급 조치 완화한다"
        }
      ]
    },
    {
      "term": "수급",
      "total": 2,
      "sourceCount": 1,
      "sources": [
        "khan"
      ],
      "examples": [
        {
          "source": "khan",
          "title": "공공차량 2부제 해제…원유 수급 숨통, 석 달 만에 정상화"
        },
        {
          "source": "khan",
          "title": "원유 수급 긴급 조치 완화한다"
        }
      ]
    },
    {
      "term": "글로벌",
      "total": 2,
      "sourceCount": 1,
      "sources": [
        "mk"
      ],
      "examples": [
        {
          "source": "mk",
          "title": "삼성전자, 한화 참여...글로벌 스테이블코인 연합체 출격"
        },
        {
          "source": "mk",
          "title": "글로벌 사모펀드 TPG … 롯데렌탈 인수 단독협상"
        }
      ]
    },
    {
      "term": "청약",
      "total": 2,
      "sourceCount": 1,
      "sources": [
        "mk"
      ],
      "examples": [
        {
          "source": "mk",
          "title": "“30억이요? 그래도 서울이잖아요”…고분양가에도 청약 열기 ‘후끈’"
        },
        {
          "source": "mk",
          "title": "장위도 노량진도 '청약 불패'"
        }
      ]
    }
  ]
}